{"order_id":5001,"customer_id":229,"amount":266.23,"order_time":"2025-09-05 05:16:56"}
{"order_id":5002,"customer_id":6,"amount":287.11,"order_time":"2025-09-05 05:26:56"}
{"order_id":5003,"customer_id":104,"amount":22.28,"order_time":"2025-09-05 05:36:56"}
{"order_id":5004,"customer_id":330,"amount":219.76,"order_time":"2025-09-05 05:46:56"}
{"order_id":5005,"customer_id":234,"amount":262.45,"order_time":"2025-09-05 05:56:56"}
{"order_id":5006,"customer_id":857,"amount":49.44,"order_time":"2025-09-05 06:06:56"}
{"order_id":5007,"customer_id":865,"amount":274.35,"order_time":"2025-09-05 06:16:56"}
{"order_id":5008,"customer_id":816,"amount":233.06,"order_time":"2025-09-05 06:26:56"}
{"order_id":5009,"customer_id":374,"amount":285.27,"order_time":"2025-09-05 06:36:56"}
{"order_id":5010,"customer_id":870,"amount":69.03,"order_time":"2025-09-05 06:46:56"}
{"order_id":5011,"customer_id":504,"amount":213.44,"order_time":"2025-09-05 06:56:56"}
{"order_id":5012,"customer_id":761,"amount":88.16,"order_time":"2025-09-05 07:06:56"}
{"order_id":5013,"customer_id":595,"amount":138.03,"order_time":"2025-09-05 07:16:56"}
{"order_id":5014,"customer_id":19,"amount":93.63,"order_time":"2025-09-05 07:26:56"}
{"order_id":5015,"customer_id":593,"amount":173.61,"order_time":"2025-09-05 07:36:56"}
{"order_id":5016,"customer_id":223,"amount":159.17,"order_time":"2025-09-05 07:46:56"}
{"order_id":5017,"customer_id":456,"amount":183.89,"order_time":"2025-09-05 07:56:56"}
{"order_id":5018,"customer_id":786,"amount":14.38,"order_time":"2025-09-05 08:06:56"}
{"order_id":5019,"customer_id":154,"amount":16.95,"order_time":"2025-09-05 08:16:56"}
{"order_id":5020,"customer_id":471,"amount":290.0,"order_time":"2025-09-05 08:26:56"}
{"order_id":5021,"customer_id":503,"amount":74.12,"order_time":"2025-09-05 08:36:56"}
{"order_id":5022,"customer_id":480,"amount":11.45,"order_time":"2025-09-05 08:46:56"}
{"order_id":5023,"customer_id":66,"amount":161.5,"order_time":"2025-09-05 08:56:56"}
{"order_id":5024,"customer_id":383,"amount":46.01,"order_time":"2025-09-05 09:06:56"}
{"order_id":5025,"customer_id":926,"amount":128.78,"order_time":"2025-09-05 09:16:56"}
{"order_id":5026,"customer_id":903,"amount":219.03,"order_time":"2025-09-05 09:26:56"}
{"order_id":5027,"customer_id":68,"amount":126.82,"order_time":"2025-09-05 09:36:56"}
{"order_id":5028,"customer_id":181,"amount":234.78,"order_time":"2025-09-05 09:46:56"}
{"order_id":5029,"customer_id":964,"amount":121.81,"order_time":"2025-09-05 09:56:56"}
{"order_id":5030,"customer_id":330,"amount":108.91,"order_time":"2025-09-05 10:06:56"}
{"order_id":5031,"customer_id":276,"amount":131.92,"order_time":"2025-09-05 10:16:56"}
{"order_id":5032,"customer_id":535,"amount":61.46,"order_time":"2025-09-05 10:26:56"}
{"order_id":5033,"customer_id":929,"amount":75.32,"order_time":"2025-09-05 10:36:56"}
{"order_id":5034,"customer_id":724,"amount":189.71,"order_time":"2025-09-05 10:46:56"}
{"order_id":5035,"customer_id":283,"amount":282.14,"order_time":"2025-09-05 10:56:56"}
{"order_id":5036,"customer_id":17,"amount":32.15,"order_time":"2025-09-05 11:06:56"}
{"order_id":5037,"customer_id":868,"amount":33.16,"order_time":"2025-09-05 11:16:56"}
{"order_id":5038,"customer_id":491,"amount":167.93,"order_time":"2025-09-05 11:26:56"}
{"order_id":5039,"customer_id":582,"amount":47.42,"order_time":"2025-09-05 11:36:56"}
{"order_id":5040,"customer_id":547,"amount":286.34,"order_time":"2025-09-05 11:46:56"}
{"order_id":5041,"customer_id":766,"amount":61.69,"order_time":"2025-09-05 11:56:56"}
{"order_id":5042,"customer_id":508,"amount":19.1,"order_time":"2025-09-05 12:06:56"}
{"order_id":5043,"customer_id":26,"amount":147.36,"order_time":"2025-09-05 12:16:56"}
{"order_id":5044,"customer_id":620,"amount":247.43,"order_time":"2025-09-05 12:26:56"}
{"order_id":5045,"customer_id":540,"amount":115.59,"order_time":"2025-09-05 12:36:56"}
{"order_id":5046,"customer_id":431,"amount":7.36,"order_time":"2025-09-05 12:46:56"}
{"order_id":5047,"customer_id":739,"amount":65.59,"order_time":"2025-09-05 12:56:56"}
{"order_id":5048,"customer_id":309,"amount":184.97,"order_time":"2025-09-05 13:06:56"}
{"order_id":5049,"customer_id":844,"amount":271.7,"order_time":"2025-09-05 13:16:56"}
{"order_id":5050,"customer_id":145,"amount":215.16,"order_time":"2025-09-05 13:26:56"}
{"order_id":5051,"customer_id":36,"amount":285.98,"order_time":"2025-09-05 13:36:56"}
{"order_id":5052,"customer_id":601,"amount":58.67,"order_time":"2025-09-05 13:46:56"}
{"order_id":5053,"customer_id":24,"amount":36.71,"order_time":"2025-09-05 13:56:56"}
{"order_id":5054,"customer_id":387,"amount":207.73,"order_time":"2025-09-05 14:06:56"}
{"order_id":5055,"customer_id":798,"amount":274.03,"order_time":"2025-09-05 14:16:56"}
{"order_id":5056,"customer_id":752,"amount":298.12,"order_time":"2025-09-05 14:26:56"}
{"order_id":5057,"customer_id":572,"amount":283.75,"order_time":"2025-09-05 14:36:56"}
{"order_id":5058,"customer_id":715,"amount":299.8,"order_time":"2025-09-05 14:46:56"}
{"order_id":5059,"customer_id":525,"amount":208.33,"order_time":"2025-09-05 14:56:56"}
{"order_id":5060,"customer_id":422,"amount":41.09,"order_time":"2025-09-05 15:06:56"}
{"order_id":5061,"customer_id":647,"amount":42.13,"order_time":"2025-09-05 15:16:56"}
{"order_id":5062,"customer_id":304,"amount":283.12,"order_time":"2025-09-05 15:26:56"}
{"order_id":5063,"customer_id":497,"amount":192.07,"order_time":"2025-09-05 15:36:56"}
{"order_id":5064,"customer_id":464,"amount":224.61,"order_time":"2025-09-05 15:46:56"}
{"order_id":5065,"customer_id":87,"amount":10.0,"order_time":"2025-09-05 15:56:56"}
{"order_id":5066,"customer_id":913,"amount":78.57,"order_time":"2025-09-05 16:06:56"}
{"order_id":5067,"customer_id":813,"amount":59.72,"order_time":"2025-09-05 16:16:56"}
{"order_id":5068,"customer_id":870,"amount":32.5,"order_time":"2025-09-05 16:26:56"}
{"order_id":5069,"customer_id":670,"amount":46.42,"order_time":"2025-09-05 16:36:56"}
{"order_id":5070,"customer_id":765,"amount":140.42,"order_time":"2025-09-05 16:46:56"}
{"order_id":5071,"customer_id":493,"amount":174.93,"order_time":"2025-09-05 16:56:56"}
{"order_id":5072,"customer_id":275,"amount":71.44,"order_time":"2025-09-05 17:06:56"}
{"order_id":5073,"customer_id":779,"amount":293.03,"order_time":"2025-09-05 17:16:56"}
{"order_id":5074,"customer_id":76,"amount":75.97,"order_time":"2025-09-05 17:26:56"}
{"order_id":5075,"customer_id":227,"amount":79.07,"order_time":"2025-09-05 17:36:56"}
{"order_id":5076,"customer_id":896,"amount":203.55,"order_time":"2025-09-05 17:46:56"}
{"order_id":5077,"customer_id":528,"amount":61.97,"order_time":"2025-09-05 17:56:56"}
{"order_id":5078,"customer_id":827,"amount":35.41,"order_time":"2025-09-05 18:06:56"}
{"order_id":5079,"customer_id":335,"amount":279.48,"order_time":"2025-09-05 18:16:56"}
{"order_id":5080,"customer_id":512,"amount":167.67,"order_time":"2025-09-05 18:26:56"}
{"order_id":5081,"customer_id":565,"amount":31.35,"order_time":"2025-09-05 18:36:56"}
{"order_id":5082,"customer_id":489,"amount":243.64,"order_time":"2025-09-05 18:46:56"}
{"order_id":5083,"customer_id":516,"amount":159.87,"order_time":"2025-09-05 18:56:56"}
{"order_id":5084,"customer_id":504,"amount":279.24,"order_time":"2025-09-05 19:06:56"}
{"order_id":5085,"customer_id":316,"amount":216.84,"order_time":"2025-09-05 19:16:56"}
{"order_id":5086,"customer_id":676,"amount":231.37,"order_time":"2025-09-05 19:26:56"}
{"order_id":5087,"customer_id":680,"amount":202.46,"order_time":"2025-09-05 19:36:56"}
{"order_id":5088,"customer_id":209,"amount":20.44,"order_time":"2025-09-05 19:46:56"}
{"order_id":5089,"customer_id":480,"amount":22.56,"order_time":"2025-09-05 19:56:56"}
{"order_id":5090,"customer_id":912,"amount":81.94,"order_time":"2025-09-05 20:06:56"}
{"order_id":5091,"customer_id":239,"amount":60.02,"order_time":"2025-09-05 20:16:56"}
{"order_id":5092,"customer_id":730,"amount":142.01,"order_time":"2025-09-05 20:26:56"}
{"order_id":5093,"customer_id":38,"amount":219.2,"order_time":"2025-09-05 20:36:56"}
{"order_id":5094,"customer_id":102,"amount":256.42,"order_time":"2025-09-05 20:46:56"}
{"order_id":5095,"customer_id":953,"amount":18.74,"order_time":"2025-09-05 20:56:56"}
{"order_id":5096,"customer_id":240,"amount":90.53,"order_time":"2025-09-05 21:06:56"}
{"order_id":5097,"customer_id":853,"amount":283.37,"order_time":"2025-09-05 21:16:56"}
{"order_id":5098,"customer_id":346,"amount":69.4,"order_time":"2025-09-05 21:26:56"}
{"order_id":5099,"customer_id":852,"amount":254.45,"order_time":"2025-09-05 21:36:56"}
{"order_id":5100,"customer_id":286,"amount":56.35,"order_time":"2025-09-05 21:46:56"}
{"order_id":5101,"customer_id":22,"amount":151.0,"order_time":"2025-09-05 21:56:56"}
{"order_id":5102,"customer_id":200,"amount":253.56,"order_time":"2025-09-05 22:06:56"}
{"order_id":5103,"customer_id":763,"amount":12.38,"order_time":"2025-09-05 22:16:56"}
{"order_id":5104,"customer_id":330,"amount":180.54,"order_time":"2025-09-05 22:26:56"}
{"order_id":5105,"customer_id":896,"amount":225.2,"order_time":"2025-09-05 22:36:56"}
{"order_id":5106,"customer_id":930,"amount":129.73,"order_time":"2025-09-05 22:46:56"}
{"order_id":5107,"customer_id":908,"amount":102.68,"order_time":"2025-09-05 22:56:56"}
{"order_id":5108,"customer_id":30,"amount":186.3,"order_time":"2025-09-05 23:06:56"}
{"order_id":5109,"customer_id":393,"amount":245.49,"order_time":"2025-09-05 23:16:56"}
{"order_id":5110,"customer_id":765,"amount":30.29,"order_time":"2025-09-05 23:26:56"}
{"order_id":5111,"customer_id":744,"amount":72.89,"order_time":"2025-09-05 23:36:56"}
{"order_id":5112,"customer_id":690,"amount":196.91,"order_time":"2025-09-05 23:46:56"}
{"order_id":5113,"customer_id":832,"amount":116.86,"order_time":"2025-09-05 23:56:56"}
{"order_id":5114,"customer_id":193,"amount":58.44,"order_time":"2025-09-06 00:06:56"}
{"order_id":5115,"customer_id":651,"amount":112.22,"order_time":"2025-09-06 00:16:56"}
{"order_id":5116,"customer_id":530,"amount":97.25,"order_time":"2025-09-06 00:26:56"}
{"order_id":5117,"customer_id":706,"amount":59.15,"order_time":"2025-09-06 00:36:56"}
{"order_id":5118,"customer_id":198,"amount":34.89,"order_time":"2025-09-06 00:46:56"}
{"order_id":5119,"customer_id":163,"amount":81.47,"order_time":"2025-09-06 00:56:56"}
{"order_id":5120,"customer_id":219,"amount":285.38,"order_time":"2025-09-06 01:06:56"}
{"order_id":5121,"customer_id":808,"amount":95.62,"order_time":"2025-09-06 01:16:56"}
{"order_id":5122,"customer_id":270,"amount":277.92,"order_time":"2025-09-06 01:26:56"}
{"order_id":5123,"customer_id":407,"amount":238.44,"order_time":"2025-09-06 01:36:56"}
{"order_id":5124,"customer_id":128,"amount":198.05,"order_time":"2025-09-06 01:46:56"}
{"order_id":5125,"customer_id":274,"amount":9.52,"order_time":"2025-09-06 01:56:56"}
{"order_id":5126,"customer_id":641,"amount":112.17,"order_time":"2025-09-06 02:06:56"}
{"order_id":5127,"customer_id":563,"amount":72.61,"order_time":"2025-09-06 02:16:56"}
{"order_id":5128,"customer_id":855,"amount":83.01,"order_time":"2025-09-06 02:26:56"}
{"order_id":5129,"customer_id":434,"amount":253.41,"order_time":"2025-09-06 02:36:56"}
{"order_id":5130,"customer_id":10,"amount":65.27,"order_time":"2025-09-06 02:46:56"}
{"order_id":5131,"customer_id":363,"amount":54.67,"order_time":"2025-09-06 02:56:56"}
{"order_id":5132,"customer_id":20,"amount":197.11,"order_time":"2025-09-06 03:06:56"}
{"order_id":5133,"customer_id":755,"amount":285.61,"order_time":"2025-09-06 03:16:56"}
{"order_id":5134,"customer_id":814,"amount":199.26,"order_time":"2025-09-06 03:26:56"}
{"order_id":5135,"customer_id":570,"amount":264.02,"order_time":"2025-09-06 03:36:56"}
{"order_id":5136,"customer_id":218,"amount":89.03,"order_time":"2025-09-06 03:46:56"}
{"order_id":5137,"customer_id":773,"amount":199.57,"order_time":"2025-09-06 03:56:56"}
{"order_id":5138,"customer_id":267,"amount":105.01,"order_time":"2025-09-06 04:06:56"}
{"order_id":5139,"customer_id":198,"amount":52.51,"order_time":"2025-09-06 04:16:56"}
{"order_id":5140,"customer_id":844,"amount":175.87,"order_time":"2025-09-06 04:26:56"}
{"order_id":5141,"customer_id":80,"amount":38.55,"order_time":"2025-09-06 04:36:56"}
{"order_id":5142,"customer_id":776,"amount":50.56,"order_time":"2025-09-06 04:46:56"}
{"order_id":5143,"customer_id":107,"amount":280.12,"order_time":"2025-09-06 04:56:56"}
{"order_id":5144,"customer_id":224,"amount":203.39,"order_time":"2025-09-06 05:06:56"}
{"order_id":5145,"customer_id":147,"amount":21.71,"order_time":"2025-09-06 05:16:56"}
{"order_id":5146,"customer_id":37,"amount":101.98,"order_time":"2025-09-06 05:26:56"}
{"order_id":5147,"customer_id":285,"amount":71.52,"order_time":"2025-09-06 05:36:56"}
{"order_id":5148,"customer_id":628,"amount":106.17,"order_time":"2025-09-06 05:46:56"}
{"order_id":5149,"customer_id":907,"amount":140.87,"order_time":"2025-09-06 05:56:56"}
{"order_id":5150,"customer_id":208,"amount":49.14,"order_time":"2025-09-06 06:06:56"}
{"order_id":5151,"customer_id":160,"amount":84.81,"order_time":"2025-09-06 06:16:56"}
{"order_id":5152,"customer_id":738,"amount":285.78,"order_time":"2025-09-06 06:26:56"}
{"order_id":5153,"customer_id":386,"amount":243.13,"order_time":"2025-09-06 06:36:56"}
{"order_id":5154,"customer_id":697,"amount":212.42,"order_time":"2025-09-06 06:46:56"}
{"order_id":5155,"customer_id":595,"amount":68.77,"order_time":"2025-09-06 06:56:56"}
{"order_id":5156,"customer_id":60,"amount":221.84,"order_time":"2025-09-06 07:06:56"}
{"order_id":5157,"customer_id":502,"amount":99.48,"order_time":"2025-09-06 07:16:56"}
{"order_id":5158,"customer_id":243,"amount":29.34,"order_time":"2025-09-06 07:26:56"}
{"order_id":5159,"customer_id":430,"amount":173.01,"order_time":"2025-09-06 07:36:56"}
{"order_id":5160,"customer_id":929,"amount":241.4,"order_time":"2025-09-06 07:46:56"}
{"order_id":5161,"customer_id":772,"amount":87.8,"order_time":"2025-09-06 07:56:56"}
{"order_id":5162,"customer_id":280,"amount":189.71,"order_time":"2025-09-06 08:06:56"}
{"order_id":5163,"customer_id":233,"amount":50.82,"order_time":"2025-09-06 08:16:56"}
{"order_id":5164,"customer_id":92,"amount":110.39,"order_time":"2025-09-06 08:26:56"}
{"order_id":5165,"customer_id":887,"amount":51.31,"order_time":"2025-09-06 08:36:56"}
{"order_id":5166,"customer_id":936,"amount":41.34,"order_time":"2025-09-06 08:46:56"}
{"order_id":5167,"customer_id":616,"amount":25.17,"order_time":"2025-09-06 08:56:56"}
{"order_id":5168,"customer_id":540,"amount":60.57,"order_time":"2025-09-06 09:06:56"}
{"order_id":5169,"customer_id":174,"amount":280.07,"order_time":"2025-09-06 09:16:56"}
{"order_id":5170,"customer_id":82,"amount":266.43,"order_time":"2025-09-06 09:26:56"}
{"order_id":5171,"customer_id":489,"amount":265.63,"order_time":"2025-09-06 09:36:56"}
{"order_id":5172,"customer_id":449,"amount":180.92,"order_time":"2025-09-06 09:46:56"}
{"order_id":5173,"customer_id":405,"amount":277.62,"order_time":"2025-09-06 09:56:56"}
{"order_id":5174,"customer_id":927,"amount":183.85,"order_time":"2025-09-06 10:06:56"}
{"order_id":5175,"customer_id":283,"amount":104.15,"order_time":"2025-09-06 10:16:56"}
{"order_id":5176,"customer_id":878,"amount":292.97,"order_time":"2025-09-06 10:26:56"}
{"order_id":5177,"customer_id":257,"amount":22.31,"order_time":"2025-09-06 10:36:56"}
{"order_id":5178,"customer_id":610,"amount":88.05,"order_time":"2025-09-06 10:46:56"}
{"order_id":5179,"customer_id":573,"amount":156.07,"order_time":"2025-09-06 10:56:56"}
{"order_id":5180,"customer_id":421,"amount":165.25,"order_time":"2025-09-06 11:06:56"}
{"order_id":5181,"customer_id":494,"amount":45.91,"order_time":"2025-09-06 11:16:56"}
{"order_id":5182,"customer_id":972,"amount":42.77,"order_time":"2025-09-06 11:26:56"}
{"order_id":5183,"customer_id":973,"amount":268.96,"order_time":"2025-09-06 11:36:56"}
{"order_id":5184,"customer_id":385,"amount":257.11,"order_time":"2025-09-06 11:46:56"}
{"order_id":5185,"customer_id":821,"amount":272.37,"order_time":"2025-09-06 11:56:56"}
{"order_id":5186,"customer_id":93,"amount":5.19,"order_time":"2025-09-06 12:06:56"}
{"order_id":5187,"customer_id":808,"amount":149.73,"order_time":"2025-09-06 12:16:56"}
{"order_id":5188,"customer_id":790,"amount":5.93,"order_time":"2025-09-06 12:26:56"}
{"order_id":5189,"customer_id":813,"amount":202.2,"order_time":"2025-09-06 12:36:56"}
{"order_id":5190,"customer_id":143,"amount":208.01,"order_time":"2025-09-06 12:46:56"}
{"order_id":5191,"customer_id":387,"amount":52.87,"order_time":"2025-09-06 12:56:56"}
{"order_id":5192,"customer_id":820,"amount":231.1,"order_time":"2025-09-06 13:06:56"}
{"order_id":5193,"customer_id":13,"amount":103.02,"order_time":"2025-09-06 13:16:56"}
{"order_id":5194,"customer_id":570,"amount":231.59,"order_time":"2025-09-06 13:26:56"}
{"order_id":5195,"customer_id":500,"amount":106.2,"order_time":"2025-09-06 13:36:56"}
{"order_id":5196,"customer_id":836,"amount":50.4,"order_time":"2025-09-06 13:46:56"}
{"order_id":5197,"customer_id":741,"amount":46.83,"order_time":"2025-09-06 13:56:56"}
{"order_id":5198,"customer_id":678,"amount":185.6,"order_time":"2025-09-06 14:06:56"}
{"order_id":5199,"customer_id":248,"amount":228.69,"order_time":"2025-09-06 14:16:56"}
{"order_id":5200,"customer_id":69,"amount":251.45,"order_time":"2025-09-06 14:26:56"}
{"order_id":5201,"customer_id":415,"amount":283.14,"order_time":"2025-09-06 14:36:56"}
{"order_id":5202,"customer_id":836,"amount":260.04,"order_time":"2025-09-06 14:46:56"}
{"order_id":5203,"customer_id":776,"amount":279.6,"order_time":"2025-09-06 14:56:56"}
{"order_id":5204,"customer_id":623,"amount":109.33,"order_time":"2025-09-06 15:06:56"}
{"order_id":5205,"customer_id":290,"amount":168.82,"order_time":"2025-09-06 15:16:56"}
{"order_id":5206,"customer_id":141,"amount":214.87,"order_time":"2025-09-06 15:26:56"}
{"order_id":5207,"customer_id":548,"amount":55.15,"order_time":"2025-09-06 15:36:56"}
{"order_id":5208,"customer_id":581,"amount":85.73,"order_time":"2025-09-06 15:46:56"}
{"order_id":5209,"customer_id":112,"amount":265.4,"order_time":"2025-09-06 15:56:56"}
{"order_id":5210,"customer_id":133,"amount":266.82,"order_time":"2025-09-06 16:06:56"}
{"order_id":5211,"customer_id":447,"amount":248.16,"order_time":"2025-09-06 16:16:56"}
{"order_id":5212,"customer_id":78,"amount":7.88,"order_time":"2025-09-06 16:26:56"}
{"order_id":5213,"customer_id":381,"amount":86.06,"order_time":"2025-09-06 16:36:56"}
{"order_id":5214,"customer_id":825,"amount":121.54,"order_time":"2025-09-06 16:46:56"}
{"order_id":5215,"customer_id":120,"amount":246.08,"order_time":"2025-09-06 16:56:56"}
{"order_id":5216,"customer_id":243,"amount":157.99,"order_time":"2025-09-06 17:06:56"}
{"order_id":5217,"customer_id":432,"amount":282.34,"order_time":"2025-09-06 17:16:56"}
{"order_id":5218,"customer_id":567,"amount":163.83,"order_time":"2025-09-06 17:26:56"}
{"order_id":5219,"customer_id":117,"amount":295.66,"order_time":"2025-09-06 17:36:56"}
{"order_id":5220,"customer_id":126,"amount":85.42,"order_time":"2025-09-06 17:46:56"}
{"order_id":5221,"customer_id":69,"amount":259.64,"order_time":"2025-09-06 17:56:56"}
{"order_id":5222,"customer_id":798,"amount":92.8,"order_time":"2025-09-06 18:06:56"}
{"order_id":5223,"customer_id":589,"amount":198.82,"order_time":"2025-09-06 18:16:56"}
{"order_id":5224,"customer_id":309,"amount":19.16,"order_time":"2025-09-06 18:26:56"}
{"order_id":5225,"customer_id":845,"amount":246.98,"order_time":"2025-09-06 18:36:56"}
{"order_id":5226,"customer_id":140,"amount":165.01,"order_time":"2025-09-06 18:46:56"}
{"order_id":5227,"customer_id":708,"amount":246.47,"order_time":"2025-09-06 18:56:56"}
{"order_id":5228,"customer_id":943,"amount":235.06,"order_time":"2025-09-06 19:06:56"}
{"order_id":5229,"customer_id":492,"amount":22.45,"order_time":"2025-09-06 19:16:56"}
{"order_id":5230,"customer_id":967,"amount":219.42,"order_time":"2025-09-06 19:26:56"}
{"order_id":5231,"customer_id":105,"amount":67.97,"order_time":"2025-09-06 19:36:56"}
{"order_id":5232,"customer_id":723,"amount":55.59,"order_time":"2025-09-06 19:46:56"}
{"order_id":5233,"customer_id":237,"amount":129.71,"order_time":"2025-09-06 19:56:56"}
{"order_id":5234,"customer_id":244,"amount":74.26,"order_time":"2025-09-06 20:06:56"}
{"order_id":5235,"customer_id":845,"amount":247.24,"order_time":"2025-09-06 20:16:56"}
{"order_id":5236,"customer_id":531,"amount":23.79,"order_time":"2025-09-06 20:26:56"}
{"order_id":5237,"customer_id":477,"amount":268.14,"order_time":"2025-09-06 20:36:56"}
{"order_id":5238,"customer_id":473,"amount":74.67,"order_time":"2025-09-06 20:46:56"}
{"order_id":5239,"customer_id":738,"amount":103.25,"order_time":"2025-09-06 20:56:56"}
{"order_id":5240,"customer_id":623,"amount":111.79,"order_time":"2025-09-06 21:06:56"}
{"order_id":5241,"customer_id":916,"amount":231.52,"order_time":"2025-09-06 21:16:56"}
{"order_id":5242,"customer_id":898,"amount":221.57,"order_time":"2025-09-06 21:26:56"}
{"order_id":5243,"customer_id":805,"amount":257.23,"order_time":"2025-09-06 21:36:56"}
{"order_id":5244,"customer_id":5,"amount":277.36,"order_time":"2025-09-06 21:46:56"}
{"order_id":5245,"customer_id":816,"amount":30.47,"order_time":"2025-09-06 21:56:56"}
{"order_id":5246,"customer_id":428,"amount":15.08,"order_time":"2025-09-06 22:06:56"}
{"order_id":5247,"customer_id":5,"amount":47.16,"order_time":"2025-09-06 22:16:56"}
{"order_id":5248,"customer_id":36,"amount":184.63,"order_time":"2025-09-06 22:26:56"}
{"order_id":5249,"customer_id":277,"amount":188.05,"order_time":"2025-09-06 22:36:56"}
{"order_id":5250,"customer_id":130,"amount":145.78,"order_time":"2025-09-06 22:46:56"}
{"order_id":5251,"customer_id":999,"amount":96.58,"order_time":"2025-09-06 22:56:56"}
{"order_id":5252,"customer_id":160,"amount":21.99,"order_time":"2025-09-06 23:06:56"}
{"order_id":5253,"customer_id":531,"amount":187.51,"order_time":"2025-09-06 23:16:56"}
{"order_id":5254,"customer_id":374,"amount":79.67,"order_time":"2025-09-06 23:26:56"}
{"order_id":5255,"customer_id":307,"amount":181.9,"order_time":"2025-09-06 23:36:56"}
{"order_id":5256,"customer_id":5,"amount":263.82,"order_time":"2025-09-06 23:46:56"}
{"order_id":5257,"customer_id":231,"amount":100.67,"order_time":"2025-09-06 23:56:56"}
{"order_id":5258,"customer_id":825,"amount":226.75,"order_time":"2025-09-07 00:06:56"}
{"order_id":5259,"customer_id":734,"amount":168.09,"order_time":"2025-09-07 00:16:56"}
{"order_id":5260,"customer_id":890,"amount":97.26,"order_time":"2025-09-07 00:26:56"}
{"order_id":5261,"customer_id":52,"amount":135.95,"order_time":"2025-09-07 00:36:56"}
{"order_id":5262,"customer_id":838,"amount":28.49,"order_time":"2025-09-07 00:46:56"}
{"order_id":5263,"customer_id":195,"amount":130.36,"order_time":"2025-09-07 00:56:56"}
{"order_id":5264,"customer_id":404,"amount":222.41,"order_time":"2025-09-07 01:06:56"}
{"order_id":5265,"customer_id":996,"amount":72.1,"order_time":"2025-09-07 01:16:56"}
{"order_id":5266,"customer_id":525,"amount":194.03,"order_time":"2025-09-07 01:26:56"}
{"order_id":5267,"customer_id":558,"amount":87.82,"order_time":"2025-09-07 01:36:56"}
{"order_id":5268,"customer_id":443,"amount":147.37,"order_time":"2025-09-07 01:46:56"}
{"order_id":5269,"customer_id":345,"amount":117.23,"order_time":"2025-09-07 01:56:56"}
{"order_id":5270,"customer_id":703,"amount":9.68,"order_time":"2025-09-07 02:06:56"}
{"order_id":5271,"customer_id":592,"amount":102.04,"order_time":"2025-09-07 02:16:56"}
{"order_id":5272,"customer_id":869,"amount":248.71,"order_time":"2025-09-07 02:26:56"}
{"order_id":5273,"customer_id":979,"amount":151.43,"order_time":"2025-09-07 02:36:56"}
{"order_id":5274,"customer_id":922,"amount":34.27,"order_time":"2025-09-07 02:46:56"}
{"order_id":5275,"customer_id":217,"amount":128.44,"order_time":"2025-09-07 02:56:56"}
{"order_id":5276,"customer_id":425,"amount":59.76,"order_time":"2025-09-07 03:06:56"}
{"order_id":5277,"customer_id":837,"amount":222.29,"order_time":"2025-09-07 03:16:56"}
{"order_id":5278,"customer_id":932,"amount":286.3,"order_time":"2025-09-07 03:26:56"}
{"order_id":5279,"customer_id":248,"amount":72.16,"order_time":"2025-09-07 03:36:56"}
{"order_id":5280,"customer_id":129,"amount":74.54,"order_time":"2025-09-07 03:46:56"}
{"order_id":5281,"customer_id":957,"amount":210.42,"order_time":"2025-09-07 03:56:56"}
{"order_id":5282,"customer_id":183,"amount":259.69,"order_time":"2025-09-07 04:06:56"}
{"order_id":5283,"customer_id":718,"amount":260.49,"order_time":"2025-09-07 04:16:56"}
{"order_id":5284,"customer_id":509,"amount":264.76,"order_time":"2025-09-07 04:26:56"}
{"order_id":5285,"customer_id":826,"amount":280.46,"order_time":"2025-09-07 04:36:56"}
{"order_id":5286,"customer_id":777,"amount":289.6,"order_time":"2025-09-07 04:46:56"}
{"order_id":5287,"customer_id":406,"amount":126.97,"order_time":"2025-09-07 04:56:56"}
{"order_id":5288,"customer_id":284,"amount":217.75,"order_time":"2025-09-07 05:06:56"}
{"order_id":5289,"customer_id":105,"amount":265.26,"order_time":"2025-09-07 05:16:56"}
{"order_id":5290,"customer_id":581,"amount":99.28,"order_time":"2025-09-07 05:26:56"}
{"order_id":5291,"customer_id":596,"amount":132.38,"order_time":"2025-09-07 05:36:56"}
{"order_id":5292,"customer_id":629,"amount":158.44,"order_time":"2025-09-07 05:46:56"}
{"order_id":5293,"customer_id":134,"amount":246.34,"order_time":"2025-09-07 05:56:56"}
{"order_id":5294,"customer_id":583,"amount":63.62,"order_time":"2025-09-07 06:06:56"}
{"order_id":5295,"customer_id":181,"amount":139.5,"order_time":"2025-09-07 06:16:56"}
{"order_id":5296,"customer_id":12,"amount":92.27,"order_time":"2025-09-07 06:26:56"}
{"order_id":5297,"customer_id":161,"amount":218.31,"order_time":"2025-09-07 06:36:56"}
{"order_id":5298,"customer_id":649,"amount":50.79,"order_time":"2025-09-07 06:46:56"}
{"order_id":5299,"customer_id":346,"amount":164.73,"order_time":"2025-09-07 06:56:56"}
{"order_id":5300,"customer_id":459,"amount":90.08,"order_time":"2025-09-07 07:06:56"}
{"order_id":5301,"customer_id":460,"amount":15.08,"order_time":"2025-09-07 07:16:56"}
{"order_id":5302,"customer_id":765,"amount":139.19,"order_time":"2025-09-07 07:26:56"}
{"order_id":5303,"customer_id":969,"amount":261.43,"order_time":"2025-09-07 07:36:56"}
{"order_id":5304,"customer_id":598,"amount":178.12,"order_time":"2025-09-07 07:46:56"}
{"order_id":5305,"customer_id":485,"amount":37.52,"order_time":"2025-09-07 07:56:56"}
{"order_id":5306,"customer_id":689,"amount":216.7,"order_time":"2025-09-07 08:06:56"}
{"order_id":5307,"customer_id":234,"amount":111.19,"order_time":"2025-09-07 08:16:56"}
{"order_id":5308,"customer_id":578,"amount":97.95,"order_time":"2025-09-07 08:26:56"}
{"order_id":5309,"customer_id":351,"amount":172.8,"order_time":"2025-09-07 08:36:56"}
{"order_id":5310,"customer_id":309,"amount":48.54,"order_time":"2025-09-07 08:46:56"}
{"order_id":5311,"customer_id":634,"amount":30.78,"order_time":"2025-09-07 08:56:56"}
{"order_id":5312,"customer_id":680,"amount":173.01,"order_time":"2025-09-07 09:06:56"}
{"order_id":5313,"customer_id":727,"amount":92.89,"order_time":"2025-09-07 09:16:56"}
{"order_id":5314,"customer_id":310,"amount":51.92,"order_time":"2025-09-07 09:26:56"}
{"order_id":5315,"customer_id":790,"amount":105.29,"order_time":"2025-09-07 09:36:56"}
{"order_id":5316,"customer_id":528,"amount":45.93,"order_time":"2025-09-07 09:46:56"}
{"order_id":5317,"customer_id":66,"amount":56.22,"order_time":"2025-09-07 09:56:56"}
{"order_id":5318,"customer_id":614,"amount":59.52,"order_time":"2025-09-07 10:06:56"}
{"order_id":5319,"customer_id":759,"amount":216.52,"order_time":"2025-09-07 10:16:56"}
{"order_id":5320,"customer_id":702,"amount":261.02,"order_time":"2025-09-07 10:26:56"}
{"order_id":5321,"customer_id":710,"amount":113.87,"order_time":"2025-09-07 10:36:56"}
{"order_id":5322,"customer_id":874,"amount":284.0,"order_time":"2025-09-07 10:46:56"}
{"order_id":5323,"customer_id":348,"amount":192.26,"order_time":"2025-09-07 10:56:56"}
{"order_id":5324,"customer_id":718,"amount":283.16,"order_time":"2025-09-07 11:06:56"}
{"order_id":5325,"customer_id":452,"amount":40.61,"order_time":"2025-09-07 11:16:56"}
{"order_id":5326,"customer_id":57,"amount":192.28,"order_time":"2025-09-07 11:26:56"}
{"order_id":5327,"customer_id":856,"amount":228.79,"order_time":"2025-09-07 11:36:56"}
{"order_id":5328,"customer_id":27,"amount":72.6,"order_time":"2025-09-07 11:46:56"}
{"order_id":5329,"customer_id":772,"amount":187.53,"order_time":"2025-09-07 11:56:56"}
{"order_id":5330,"customer_id":889,"amount":132.28,"order_time":"2025-09-07 12:06:56"}
{"order_id":5331,"customer_id":879,"amount":214.87,"order_time":"2025-09-07 12:16:56"}
{"order_id":5332,"customer_id":53,"amount":122.15,"order_time":"2025-09-07 12:26:56"}
{"order_id":5333,"customer_id":741,"amount":13.67,"order_time":"2025-09-07 12:36:56"}
{"order_id":5334,"customer_id":259,"amount":139.31,"order_time":"2025-09-07 12:46:56"}
{"order_id":5335,"customer_id":627,"amount":73.75,"order_time":"2025-09-07 12:56:56"}
{"order_id":5336,"customer_id":203,"amount":124.71,"order_time":"2025-09-07 13:06:56"}
{"order_id":5337,"customer_id":5,"amount":145.66,"order_time":"2025-09-07 13:16:56"}
{"order_id":5338,"customer_id":9,"amount":35.68,"order_time":"2025-09-07 13:26:56"}
{"order_id":5339,"customer_id":863,"amount":117.43,"order_time":"2025-09-07 13:36:56"}
{"order_id":5340,"customer_id":697,"amount":122.09,"order_time":"2025-09-07 13:46:56"}
{"order_id":5341,"customer_id":143,"amount":10.04,"order_time":"2025-09-07 13:56:56"}
{"order_id":5342,"customer_id":845,"amount":208.01,"order_time":"2025-09-07 14:06:56"}
{"order_id":5343,"customer_id":679,"amount":206.97,"order_time":"2025-09-07 14:16:56"}
{"order_id":5344,"customer_id":812,"amount":160.64,"order_time":"2025-09-07 14:26:56"}
{"order_id":5345,"customer_id":256,"amount":267.53,"order_time":"2025-09-07 14:36:56"}
{"order_id":5346,"customer_id":654,"amount":242.83,"order_time":"2025-09-07 14:46:56"}
{"order_id":5347,"customer_id":417,"amount":252.77,"order_time":"2025-09-07 14:56:56"}
{"order_id":5348,"customer_id":365,"amount":133.81,"order_time":"2025-09-07 15:06:56"}
{"order_id":5349,"customer_id":574,"amount":96.06,"order_time":"2025-09-07 15:16:56"}
{"order_id":5350,"customer_id":449,"amount":71.88,"order_time":"2025-09-07 15:26:56"}
{"order_id":5351,"customer_id":987,"amount":298.74,"order_time":"2025-09-07 15:36:56"}
{"order_id":5352,"customer_id":351,"amount":165.88,"order_time":"2025-09-07 15:46:56"}
{"order_id":5353,"customer_id":235,"amount":266.19,"order_time":"2025-09-07 15:56:56"}
{"order_id":5354,"customer_id":510,"amount":190.56,"order_time":"2025-09-07 16:06:56"}
{"order_id":5355,"customer_id":809,"amount":110.91,"order_time":"2025-09-07 16:16:56"}
{"order_id":5356,"customer_id":206,"amount":211.37,"order_time":"2025-09-07 16:26:56"}
{"order_id":5357,"customer_id":381,"amount":283.21,"order_time":"2025-09-07 16:36:56"}
{"order_id":5358,"customer_id":707,"amount":83.39,"order_time":"2025-09-07 16:46:56"}
{"order_id":5359,"customer_id":894,"amount":169.84,"order_time":"2025-09-07 16:56:56"}
{"order_id":5360,"customer_id":196,"amount":180.59,"order_time":"2025-09-07 17:06:56"}
{"order_id":5361,"customer_id":816,"amount":219.18,"order_time":"2025-09-07 17:16:56"}
{"order_id":5362,"customer_id":738,"amount":40.45,"order_time":"2025-09-07 17:26:56"}
{"order_id":5363,"customer_id":387,"amount":25.28,"order_time":"2025-09-07 17:36:56"}
{"order_id":5364,"customer_id":294,"amount":212.05,"order_time":"2025-09-07 17:46:56"}
{"order_id":5365,"customer_id":632,"amount":77.59,"order_time":"2025-09-07 17:56:56"}
{"order_id":5366,"customer_id":671,"amount":24.53,"order_time":"2025-09-07 18:06:56"}
{"order_id":5367,"customer_id":662,"amount":296.36,"order_time":"2025-09-07 18:16:56"}
{"order_id":5368,"customer_id":190,"amount":229.22,"order_time":"2025-09-07 18:26:56"}
{"order_id":5369,"customer_id":28,"amount":167.82,"order_time":"2025-09-07 18:36:56"}
{"order_id":5370,"customer_id":183,"amount":155.94,"order_time":"2025-09-07 18:46:56"}
{"order_id":5371,"customer_id":131,"amount":161.56,"order_time":"2025-09-07 18:56:56"}
{"order_id":5372,"customer_id":510,"amount":29.24,"order_time":"2025-09-07 19:06:56"}
{"order_id":5373,"customer_id":371,"amount":228.16,"order_time":"2025-09-07 19:16:56"}
{"order_id":5374,"customer_id":936,"amount":211.55,"order_time":"2025-09-07 19:26:56"}
{"order_id":5375,"customer_id":372,"amount":197.38,"order_time":"2025-09-07 19:36:56"}
{"order_id":5376,"customer_id":999,"amount":294.97,"order_time":"2025-09-07 19:46:56"}
{"order_id":5377,"customer_id":497,"amount":124.68,"order_time":"2025-09-07 19:56:56"}
{"order_id":5378,"customer_id":272,"amount":27.45,"order_time":"2025-09-07 20:06:56"}
{"order_id":5379,"customer_id":824,"amount":296.46,"order_time":"2025-09-07 20:16:56"}
{"order_id":5380,"customer_id":578,"amount":77.7,"order_time":"2025-09-07 20:26:56"}
{"order_id":5381,"customer_id":705,"amount":205.42,"order_time":"2025-09-07 20:36:56"}
{"order_id":5382,"customer_id":381,"amount":277.95,"order_time":"2025-09-07 20:46:56"}
{"order_id":5383,"customer_id":728,"amount":10.68,"order_time":"2025-09-07 20:56:56"}
{"order_id":5384,"customer_id":101,"amount":63.7,"order_time":"2025-09-07 21:06:56"}
{"order_id":5385,"customer_id":195,"amount":156.73,"order_time":"2025-09-07 21:16:56"}
{"order_id":5386,"customer_id":9,"amount":218.59,"order_time":"2025-09-07 21:26:56"}
{"order_id":5387,"customer_id":256,"amount":142.65,"order_time":"2025-09-07 21:36:56"}
{"order_id":5388,"customer_id":662,"amount":212.71,"order_time":"2025-09-07 21:46:56"}
{"order_id":5389,"customer_id":82,"amount":119.18,"order_time":"2025-09-07 21:56:56"}
{"order_id":5390,"customer_id":218,"amount":281.01,"order_time":"2025-09-07 22:06:56"}
{"order_id":5391,"customer_id":162,"amount":105.88,"order_time":"2025-09-07 22:16:56"}
{"order_id":5392,"customer_id":265,"amount":206.05,"order_time":"2025-09-07 22:26:56"}
{"order_id":5393,"customer_id":296,"amount":53.69,"order_time":"2025-09-07 22:36:56"}
{"order_id":5394,"customer_id":647,"amount":265.27,"order_time":"2025-09-07 22:46:56"}
{"order_id":5395,"customer_id":972,"amount":37.64,"order_time":"2025-09-07 22:56:56"}
{"order_id":5396,"customer_id":262,"amount":119.86,"order_time":"2025-09-07 23:06:56"}
{"order_id":5397,"customer_id":268,"amount":151.0,"order_time":"2025-09-07 23:16:56"}
{"order_id":5398,"customer_id":694,"amount":100.9,"order_time":"2025-09-07 23:26:56"}
{"order_id":5399,"customer_id":649,"amount":161.56,"order_time":"2025-09-07 23:36:56"}
{"order_id":5400,"customer_id":64,"amount":253.81,"order_time":"2025-09-07 23:46:56"}
{"order_id":5401,"customer_id":901,"amount":246.27,"order_time":"2025-09-07 23:56:56"}
{"order_id":5402,"customer_id":152,"amount":251.58,"order_time":"2025-09-08 00:06:56"}
{"order_id":5403,"customer_id":343,"amount":32.34,"order_time":"2025-09-08 00:16:56"}
{"order_id":5404,"customer_id":157,"amount":262.03,"order_time":"2025-09-08 00:26:56"}
{"order_id":5405,"customer_id":861,"amount":156.89,"order_time":"2025-09-08 00:36:56"}
{"order_id":5406,"customer_id":751,"amount":142.26,"order_time":"2025-09-08 00:46:56"}
{"order_id":5407,"customer_id":649,"amount":216.88,"order_time":"2025-09-08 00:56:56"}
{"order_id":5408,"customer_id":892,"amount":294.81,"order_time":"2025-09-08 01:06:56"}
{"order_id":5409,"customer_id":489,"amount":215.32,"order_time":"2025-09-08 01:16:56"}
{"order_id":5410,"customer_id":518,"amount":281.06,"order_time":"2025-09-08 01:26:56"}
{"order_id":5411,"customer_id":684,"amount":43.32,"order_time":"2025-09-08 01:36:56"}
{"order_id":5412,"customer_id":686,"amount":9.33,"order_time":"2025-09-08 01:46:56"}
{"order_id":5413,"customer_id":208,"amount":248.75,"order_time":"2025-09-08 01:56:56"}
{"order_id":5414,"customer_id":836,"amount":127.26,"order_time":"2025-09-08 02:06:56"}
{"order_id":5415,"customer_id":210,"amount":238.96,"order_time":"2025-09-08 02:16:56"}
{"order_id":5416,"customer_id":941,"amount":35.92,"order_time":"2025-09-08 02:26:56"}
{"order_id":5417,"customer_id":523,"amount":85.38,"order_time":"2025-09-08 02:36:56"}
{"order_id":5418,"customer_id":789,"amount":290.44,"order_time":"2025-09-08 02:46:56"}
{"order_id":5419,"customer_id":798,"amount":250.63,"order_time":"2025-09-08 02:56:56"}
{"order_id":5420,"customer_id":379,"amount":102.13,"order_time":"2025-09-08 03:06:56"}
{"order_id":5421,"customer_id":984,"amount":110.21,"order_time":"2025-09-08 03:16:56"}
{"order_id":5422,"customer_id":639,"amount":173.79,"order_time":"2025-09-08 03:26:56"}
{"order_id":5423,"customer_id":729,"amount":77.37,"order_time":"2025-09-08 03:36:56"}
{"order_id":5424,"customer_id":296,"amount":270.53,"order_time":"2025-09-08 03:46:56"}
{"order_id":5425,"customer_id":571,"amount":26.53,"order_time":"2025-09-08 03:56:56"}
{"order_id":5426,"customer_id":458,"amount":184.09,"order_time":"2025-09-08 04:06:56"}
{"order_id":5427,"customer_id":894,"amount":105.35,"order_time":"2025-09-08 04:16:56"}
{"order_id":5428,"customer_id":384,"amount":56.94,"order_time":"2025-09-08 04:26:56"}
{"order_id":5429,"customer_id":579,"amount":6.27,"order_time":"2025-09-08 04:36:56"}
{"order_id":5430,"customer_id":107,"amount":65.34,"order_time":"2025-09-08 04:46:56"}
{"order_id":5431,"customer_id":154,"amount":48.43,"order_time":"2025-09-08 04:56:56"}
{"order_id":5432,"customer_id":573,"amount":156.86,"order_time":"2025-09-08 05:06:56"}
{"order_id":5433,"customer_id":660,"amount":286.32,"order_time":"2025-09-08 05:16:56"}
{"order_id":5434,"customer_id":4,"amount":145.19,"order_time":"2025-09-08 05:26:56"}
{"order_id":5435,"customer_id":882,"amount":255.21,"order_time":"2025-09-08 05:36:56"}
{"order_id":5436,"customer_id":794,"amount":76.21,"order_time":"2025-09-08 05:46:56"}
{"order_id":5437,"customer_id":390,"amount":251.43,"order_time":"2025-09-08 05:56:56"}
{"order_id":5438,"customer_id":528,"amount":61.62,"order_time":"2025-09-08 06:06:56"}
{"order_id":5439,"customer_id":17,"amount":115.13,"order_time":"2025-09-08 06:16:56"}
{"order_id":5440,"customer_id":465,"amount":141.04,"order_time":"2025-09-08 06:26:56"}
{"order_id":5441,"customer_id":342,"amount":42.84,"order_time":"2025-09-08 06:36:56"}
{"order_id":5442,"customer_id":438,"amount":106.23,"order_time":"2025-09-08 06:46:56"}
{"order_id":5443,"customer_id":331,"amount":18.72,"order_time":"2025-09-08 06:56:56"}
{"order_id":5444,"customer_id":132,"amount":132.22,"order_time":"2025-09-08 07:06:56"}
{"order_id":5445,"customer_id":832,"amount":177.46,"order_time":"2025-09-08 07:16:56"}
{"order_id":5446,"customer_id":34,"amount":42.26,"order_time":"2025-09-08 07:26:56"}
{"order_id":5447,"customer_id":809,"amount":80.8,"order_time":"2025-09-08 07:36:56"}
{"order_id":5448,"customer_id":998,"amount":280.6,"order_time":"2025-09-08 07:46:56"}
{"order_id":5449,"customer_id":510,"amount":27.13,"order_time":"2025-09-08 07:56:56"}
{"order_id":5450,"customer_id":778,"amount":204.46,"order_time":"2025-09-08 08:06:56"}
{"order_id":5451,"customer_id":502,"amount":132.18,"order_time":"2025-09-08 08:16:56"}
{"order_id":5452,"customer_id":423,"amount":120.96,"order_time":"2025-09-08 08:26:56"}
{"order_id":5453,"customer_id":727,"amount":57.38,"order_time":"2025-09-08 08:36:56"}
{"order_id":5454,"customer_id":291,"amount":265.89,"order_time":"2025-09-08 08:46:56"}
{"order_id":5455,"customer_id":220,"amount":174.24,"order_time":"2025-09-08 08:56:56"}
{"order_id":5456,"customer_id":698,"amount":260.21,"order_time":"2025-09-08 09:06:56"}
{"order_id":5457,"customer_id":529,"amount":160.29,"order_time":"2025-09-08 09:16:56"}
{"order_id":5458,"customer_id":292,"amount":122.61,"order_time":"2025-09-08 09:26:56"}
{"order_id":5459,"customer_id":858,"amount":297.03,"order_time":"2025-09-08 09:36:56"}
{"order_id":5460,"customer_id":838,"amount":157.22,"order_time":"2025-09-08 09:46:56"}
{"order_id":5461,"customer_id":411,"amount":77.24,"order_time":"2025-09-08 09:56:56"}
{"order_id":5462,"customer_id":208,"amount":43.62,"order_time":"2025-09-08 10:06:56"}
{"order_id":5463,"customer_id":173,"amount":101.24,"order_time":"2025-09-08 10:16:56"}
{"order_id":5464,"customer_id":230,"amount":161.49,"order_time":"2025-09-08 10:26:56"}
{"order_id":5465,"customer_id":908,"amount":215.91,"order_time":"2025-09-08 10:36:56"}
{"order_id":5466,"customer_id":802,"amount":169.66,"order_time":"2025-09-08 10:46:56"}
{"order_id":5467,"customer_id":428,"amount":219.09,"order_time":"2025-09-08 10:56:56"}
{"order_id":5468,"customer_id":471,"amount":61.12,"order_time":"2025-09-08 11:06:56"}
{"order_id":5469,"customer_id":48,"amount":251.01,"order_time":"2025-09-08 11:16:56"}
{"order_id":5470,"customer_id":791,"amount":31.35,"order_time":"2025-09-08 11:26:56"}
{"order_id":5471,"customer_id":729,"amount":43.74,"order_time":"2025-09-08 11:36:56"}
{"order_id":5472,"customer_id":746,"amount":190.2,"order_time":"2025-09-08 11:46:56"}
{"order_id":5473,"customer_id":339,"amount":138.78,"order_time":"2025-09-08 11:56:56"}
{"order_id":5474,"customer_id":817,"amount":30.73,"order_time":"2025-09-08 12:06:56"}
{"order_id":5475,"customer_id":96,"amount":141.69,"order_time":"2025-09-08 12:16:56"}
{"order_id":5476,"customer_id":801,"amount":248.34,"order_time":"2025-09-08 12:26:56"}
{"order_id":5477,"customer_id":166,"amount":211.63,"order_time":"2025-09-08 12:36:56"}
{"order_id":5478,"customer_id":464,"amount":82.5,"order_time":"2025-09-08 12:46:56"}
{"order_id":5479,"customer_id":295,"amount":121.45,"order_time":"2025-09-08 12:56:56"}
{"order_id":5480,"customer_id":224,"amount":158.18,"order_time":"2025-09-08 13:06:56"}
{"order_id":5481,"customer_id":728,"amount":220.06,"order_time":"2025-09-08 13:16:56"}
{"order_id":5482,"customer_id":377,"amount":32.31,"order_time":"2025-09-08 13:26:56"}
{"order_id":5483,"customer_id":751,"amount":267.83,"order_time":"2025-09-08 13:36:56"}
{"order_id":5484,"customer_id":518,"amount":243.01,"order_time":"2025-09-08 13:46:56"}
{"order_id":5485,"customer_id":267,"amount":277.64,"order_time":"2025-09-08 13:56:56"}
{"order_id":5486,"customer_id":628,"amount":47.4,"order_time":"2025-09-08 14:06:56"}
{"order_id":5487,"customer_id":408,"amount":229.84,"order_time":"2025-09-08 14:16:56"}
{"order_id":5488,"customer_id":490,"amount":136.36,"order_time":"2025-09-08 14:26:56"}
{"order_id":5489,"customer_id":583,"amount":224.88,"order_time":"2025-09-08 14:36:56"}
{"order_id":5490,"customer_id":821,"amount":253.11,"order_time":"2025-09-08 14:46:56"}
{"order_id":5491,"customer_id":681,"amount":153.24,"order_time":"2025-09-08 14:56:56"}
{"order_id":5492,"customer_id":31,"amount":134.65,"order_time":"2025-09-08 15:06:56"}
{"order_id":5493,"customer_id":546,"amount":187.56,"order_time":"2025-09-08 15:16:56"}
{"order_id":5494,"customer_id":214,"amount":190.4,"order_time":"2025-09-08 15:26:56"}
{"order_id":5495,"customer_id":920,"amount":119.49,"order_time":"2025-09-08 15:36:56"}
{"order_id":5496,"customer_id":422,"amount":266.57,"order_time":"2025-09-08 15:46:56"}
{"order_id":5497,"customer_id":962,"amount":7.42,"order_time":"2025-09-08 15:56:56"}
{"order_id":5498,"customer_id":947,"amount":16.86,"order_time":"2025-09-08 16:06:56"}
{"order_id":5499,"customer_id":459,"amount":169.89,"order_time":"2025-09-08 16:16:56"}
{"order_id":5500,"customer_id":266,"amount":294.59,"order_time":"2025-09-08 16:26:56"}
{"order_id":5501,"customer_id":815,"amount":133.9,"order_time":"2025-09-08 16:36:56"}
{"order_id":5502,"customer_id":227,"amount":22.12,"order_time":"2025-09-08 16:46:56"}
{"order_id":5503,"customer_id":571,"amount":60.25,"order_time":"2025-09-08 16:56:56"}
{"order_id":5504,"customer_id":772,"amount":148.7,"order_time":"2025-09-08 17:06:56"}
{"order_id":5505,"customer_id":434,"amount":81.49,"order_time":"2025-09-08 17:16:56"}
{"order_id":5506,"customer_id":320,"amount":119.49,"order_time":"2025-09-08 17:26:56"}
{"order_id":5507,"customer_id":103,"amount":166.4,"order_time":"2025-09-08 17:36:56"}
{"order_id":5508,"customer_id":198,"amount":5.48,"order_time":"2025-09-08 17:46:56"}
{"order_id":5509,"customer_id":699,"amount":148.28,"order_time":"2025-09-08 17:56:56"}
{"order_id":5510,"customer_id":122,"amount":249.95,"order_time":"2025-09-08 18:06:56"}
{"order_id":5511,"customer_id":939,"amount":284.67,"order_time":"2025-09-08 18:16:56"}
{"order_id":5512,"customer_id":827,"amount":102.62,"order_time":"2025-09-08 18:26:56"}
{"order_id":5513,"customer_id":334,"amount":251.38,"order_time":"2025-09-08 18:36:56"}
{"order_id":5514,"customer_id":454,"amount":239.06,"order_time":"2025-09-08 18:46:56"}
{"order_id":5515,"customer_id":473,"amount":250.61,"order_time":"2025-09-08 18:56:56"}
{"order_id":5516,"customer_id":903,"amount":154.89,"order_time":"2025-09-08 19:06:56"}
{"order_id":5517,"customer_id":842,"amount":22.63,"order_time":"2025-09-08 19:16:56"}
{"order_id":5518,"customer_id":173,"amount":98.02,"order_time":"2025-09-08 19:26:56"}
{"order_id":5519,"customer_id":384,"amount":73.35,"order_time":"2025-09-08 19:36:56"}
{"order_id":5520,"customer_id":48,"amount":249.21,"order_time":"2025-09-08 19:46:56"}
{"order_id":5521,"customer_id":323,"amount":51.35,"order_time":"2025-09-08 19:56:56"}
{"order_id":5522,"customer_id":998,"amount":49.75,"order_time":"2025-09-08 20:06:56"}
{"order_id":5523,"customer_id":721,"amount":71.96,"order_time":"2025-09-08 20:16:56"}
{"order_id":5524,"customer_id":91,"amount":255.29,"order_time":"2025-09-08 20:26:56"}
{"order_id":5525,"customer_id":562,"amount":254.77,"order_time":"2025-09-08 20:36:56"}
{"order_id":5526,"customer_id":650,"amount":180.88,"order_time":"2025-09-08 20:46:56"}
{"order_id":5527,"customer_id":37,"amount":25.74,"order_time":"2025-09-08 20:56:56"}
{"order_id":5528,"customer_id":557,"amount":14.8,"order_time":"2025-09-08 21:06:56"}
{"order_id":5529,"customer_id":681,"amount":265.61,"order_time":"2025-09-08 21:16:56"}
{"order_id":5530,"customer_id":355,"amount":138.01,"order_time":"2025-09-08 21:26:56"}
{"order_id":5531,"customer_id":384,"amount":18.16,"order_time":"2025-09-08 21:36:56"}
{"order_id":5532,"customer_id":629,"amount":58.53,"order_time":"2025-09-08 21:46:56"}
{"order_id":5533,"customer_id":278,"amount":150.14,"order_time":"2025-09-08 21:56:56"}
{"order_id":5534,"customer_id":655,"amount":291.47,"order_time":"2025-09-08 22:06:56"}
{"order_id":5535,"customer_id":6,"amount":151.66,"order_time":"2025-09-08 22:16:56"}
{"order_id":5536,"customer_id":341,"amount":54.7,"order_time":"2025-09-08 22:26:56"}
{"order_id":5537,"customer_id":748,"amount":47.7,"order_time":"2025-09-08 22:36:56"}
{"order_id":5538,"customer_id":82,"amount":242.78,"order_time":"2025-09-08 22:46:56"}
{"order_id":5539,"customer_id":529,"amount":230.79,"order_time":"2025-09-08 22:56:56"}
{"order_id":5540,"customer_id":729,"amount":130.16,"order_time":"2025-09-08 23:06:56"}
{"order_id":5541,"customer_id":334,"amount":29.73,"order_time":"2025-09-08 23:16:56"}
{"order_id":5542,"customer_id":382,"amount":224.14,"order_time":"2025-09-08 23:26:56"}
{"order_id":5543,"customer_id":216,"amount":297.57,"order_time":"2025-09-08 23:36:56"}
{"order_id":5544,"customer_id":781,"amount":132.45,"order_time":"2025-09-08 23:46:56"}
{"order_id":5545,"customer_id":460,"amount":48.06,"order_time":"2025-09-08 23:56:56"}
{"order_id":5546,"customer_id":273,"amount":268.79,"order_time":"2025-09-09 00:06:56"}
{"order_id":5547,"customer_id":236,"amount":257.46,"order_time":"2025-09-09 00:16:56"}
{"order_id":5548,"customer_id":307,"amount":263.95,"order_time":"2025-09-09 00:26:56"}
{"order_id":5549,"customer_id":315,"amount":68.25,"order_time":"2025-09-09 00:36:56"}
{"order_id":5550,"customer_id":697,"amount":16.18,"order_time":"2025-09-09 00:46:56"}
{"order_id":5551,"customer_id":342,"amount":43.48,"order_time":"2025-09-09 00:56:56"}
{"order_id":5552,"customer_id":931,"amount":213.45,"order_time":"2025-09-09 01:06:56"}
{"order_id":5553,"customer_id":42,"amount":274.18,"order_time":"2025-09-09 01:16:56"}
{"order_id":5554,"customer_id":698,"amount":297.9,"order_time":"2025-09-09 01:26:56"}
{"order_id":5555,"customer_id":973,"amount":207.88,"order_time":"2025-09-09 01:36:56"}
{"order_id":5556,"customer_id":939,"amount":135.26,"order_time":"2025-09-09 01:46:56"}
{"order_id":5557,"customer_id":797,"amount":208.42,"order_time":"2025-09-09 01:56:56"}
{"order_id":5558,"customer_id":596,"amount":243.9,"order_time":"2025-09-09 02:06:56"}
{"order_id":5559,"customer_id":743,"amount":71.37,"order_time":"2025-09-09 02:16:56"}
{"order_id":5560,"customer_id":734,"amount":11.75,"order_time":"2025-09-09 02:26:56"}
{"order_id":5561,"customer_id":719,"amount":206.56,"order_time":"2025-09-09 02:36:56"}
{"order_id":5562,"customer_id":359,"amount":247.63,"order_time":"2025-09-09 02:46:56"}
{"order_id":5563,"customer_id":748,"amount":74.08,"order_time":"2025-09-09 02:56:56"}
{"order_id":5564,"customer_id":460,"amount":58.77,"order_time":"2025-09-09 03:06:56"}
{"order_id":5565,"customer_id":336,"amount":244.47,"order_time":"2025-09-09 03:16:56"}
{"order_id":5566,"customer_id":632,"amount":195.83,"order_time":"2025-09-09 03:26:56"}
{"order_id":5567,"customer_id":562,"amount":11.68,"order_time":"2025-09-09 03:36:56"}
{"order_id":5568,"customer_id":730,"amount":99.91,"order_time":"2025-09-09 03:46:56"}
{"order_id":5569,"customer_id":498,"amount":138.9,"order_time":"2025-09-09 03:56:56"}
{"order_id":5570,"customer_id":394,"amount":24.49,"order_time":"2025-09-09 04:06:56"}
{"order_id":5571,"customer_id":857,"amount":288.63,"order_time":"2025-09-09 04:16:56"}
{"order_id":5572,"customer_id":383,"amount":97.86,"order_time":"2025-09-09 04:26:56"}
{"order_id":5573,"customer_id":446,"amount":19.4,"order_time":"2025-09-09 04:36:56"}
{"order_id":5574,"customer_id":559,"amount":183.13,"order_time":"2025-09-09 04:46:56"}
{"order_id":5575,"customer_id":623,"amount":91.8,"order_time":"2025-09-09 04:56:56"}
{"order_id":5576,"customer_id":414,"amount":252.19,"order_time":"2025-09-09 05:06:56"}
{"order_id":5577,"customer_id":386,"amount":248.7,"order_time":"2025-09-09 05:16:56"}
{"order_id":5578,"customer_id":89,"amount":129.08,"order_time":"2025-09-09 05:26:56"}
{"order_id":5579,"customer_id":891,"amount":107.74,"order_time":"2025-09-09 05:36:56"}
{"order_id":5580,"customer_id":505,"amount":80.55,"order_time":"2025-09-09 05:46:56"}
{"order_id":5581,"customer_id":205,"amount":55.94,"order_time":"2025-09-09 05:56:56"}
{"order_id":5582,"customer_id":237,"amount":285.35,"order_time":"2025-09-09 06:06:56"}
{"order_id":5583,"customer_id":547,"amount":286.28,"order_time":"2025-09-09 06:16:56"}
{"order_id":5584,"customer_id":719,"amount":218.99,"order_time":"2025-09-09 06:26:56"}
{"order_id":5585,"customer_id":209,"amount":171.22,"order_time":"2025-09-09 06:36:56"}
{"order_id":5586,"customer_id":328,"amount":189.18,"order_time":"2025-09-09 06:46:56"}
{"order_id":5587,"customer_id":754,"amount":128.94,"order_time":"2025-09-09 06:56:56"}
{"order_id":5588,"customer_id":350,"amount":163.81,"order_time":"2025-09-09 07:06:56"}
{"order_id":5589,"customer_id":725,"amount":16.25,"order_time":"2025-09-09 07:16:56"}
{"order_id":5590,"customer_id":747,"amount":36.46,"order_time":"2025-09-09 07:26:56"}
{"order_id":5591,"customer_id":488,"amount":38.85,"order_time":"2025-09-09 07:36:56"}
{"order_id":5592,"customer_id":762,"amount":110.07,"order_time":"2025-09-09 07:46:56"}
{"order_id":5593,"customer_id":611,"amount":242.28,"order_time":"2025-09-09 07:56:56"}
{"order_id":5594,"customer_id":633,"amount":77.87,"order_time":"2025-09-09 08:06:56"}
{"order_id":5595,"customer_id":871,"amount":76.51,"order_time":"2025-09-09 08:16:56"}
{"order_id":5596,"customer_id":323,"amount":103.52,"order_time":"2025-09-09 08:26:56"}
{"order_id":5597,"customer_id":825,"amount":149.47,"order_time":"2025-09-09 08:36:56"}
{"order_id":5598,"customer_id":211,"amount":121.35,"order_time":"2025-09-09 08:46:56"}
{"order_id":5599,"customer_id":137,"amount":268.7,"order_time":"2025-09-09 08:56:56"}
{"order_id":5600,"customer_id":737,"amount":107.0,"order_time":"2025-09-09 09:06:56"}
{"order_id":5601,"customer_id":704,"amount":194.61,"order_time":"2025-09-09 09:16:56"}
{"order_id":5602,"customer_id":721,"amount":146.19,"order_time":"2025-09-09 09:26:56"}
{"order_id":5603,"customer_id":487,"amount":190.97,"order_time":"2025-09-09 09:36:56"}
{"order_id":5604,"customer_id":890,"amount":114.9,"order_time":"2025-09-09 09:46:56"}
{"order_id":5605,"customer_id":353,"amount":226.9,"order_time":"2025-09-09 09:56:56"}
{"order_id":5606,"customer_id":618,"amount":70.19,"order_time":"2025-09-09 10:06:56"}
{"order_id":5607,"customer_id":895,"amount":287.79,"order_time":"2025-09-09 10:16:56"}
{"order_id":5608,"customer_id":324,"amount":208.9,"order_time":"2025-09-09 10:26:56"}
{"order_id":5609,"customer_id":562,"amount":227.17,"order_time":"2025-09-09 10:36:56"}
{"order_id":5610,"customer_id":826,"amount":54.77,"order_time":"2025-09-09 10:46:56"}
{"order_id":5611,"customer_id":728,"amount":40.37,"order_time":"2025-09-09 10:56:56"}
{"order_id":5612,"customer_id":634,"amount":230.68,"order_time":"2025-09-09 11:06:56"}
{"order_id":5613,"customer_id":32,"amount":87.11,"order_time":"2025-09-09 11:16:56"}
{"order_id":5614,"customer_id":813,"amount":104.86,"order_time":"2025-09-09 11:26:56"}
{"order_id":5615,"customer_id":109,"amount":190.16,"order_time":"2025-09-09 11:36:56"}
{"order_id":5616,"customer_id":457,"amount":202.51,"order_time":"2025-09-09 11:46:56"}
{"order_id":5617,"customer_id":841,"amount":154.86,"order_time":"2025-09-09 11:56:56"}
{"order_id":5618,"customer_id":605,"amount":74.07,"order_time":"2025-09-09 12:06:56"}
{"order_id":5619,"customer_id":721,"amount":23.66,"order_time":"2025-09-09 12:16:56"}
{"order_id":5620,"customer_id":182,"amount":118.19,"order_time":"2025-09-09 12:26:56"}
{"order_id":5621,"customer_id":851,"amount":210.04,"order_time":"2025-09-09 12:36:56"}
{"order_id":5622,"customer_id":79,"amount":38.52,"order_time":"2025-09-09 12:46:56"}
{"order_id":5623,"customer_id":314,"amount":241.25,"order_time":"2025-09-09 12:56:56"}
{"order_id":5624,"customer_id":737,"amount":13.48,"order_time":"2025-09-09 13:06:56"}
{"order_id":5625,"customer_id":108,"amount":65.19,"order_time":"2025-09-09 13:16:56"}
{"order_id":5626,"customer_id":979,"amount":121.15,"order_time":"2025-09-09 13:26:56"}
{"order_id":5627,"customer_id":406,"amount":7.31,"order_time":"2025-09-09 13:36:56"}
{"order_id":5628,"customer_id":884,"amount":260.4,"order_time":"2025-09-09 13:46:56"}
{"order_id":5629,"customer_id":712,"amount":251.19,"order_time":"2025-09-09 13:56:56"}
{"order_id":5630,"customer_id":62,"amount":132.99,"order_time":"2025-09-09 14:06:56"}
{"order_id":5631,"customer_id":516,"amount":165.66,"order_time":"2025-09-09 14:16:56"}
{"order_id":5632,"customer_id":284,"amount":73.15,"order_time":"2025-09-09 14:26:56"}
{"order_id":5633,"customer_id":911,"amount":161.51,"order_time":"2025-09-09 14:36:56"}
{"order_id":5634,"customer_id":289,"amount":177.66,"order_time":"2025-09-09 14:46:56"}
{"order_id":5635,"customer_id":766,"amount":51.75,"order_time":"2025-09-09 14:56:56"}
{"order_id":5636,"customer_id":613,"amount":45.4,"order_time":"2025-09-09 15:06:56"}
{"order_id":5637,"customer_id":180,"amount":231.64,"order_time":"2025-09-09 15:16:56"}
{"order_id":5638,"customer_id":790,"amount":15.48,"order_time":"2025-09-09 15:26:56"}
{"order_id":5639,"customer_id":784,"amount":256.78,"order_time":"2025-09-09 15:36:56"}
{"order_id":5640,"customer_id":768,"amount":182.09,"order_time":"2025-09-09 15:46:56"}
{"order_id":5641,"customer_id":981,"amount":17.76,"order_time":"2025-09-09 15:56:56"}
{"order_id":5642,"customer_id":977,"amount":168.08,"order_time":"2025-09-09 16:06:56"}
{"order_id":5643,"customer_id":130,"amount":236.48,"order_time":"2025-09-09 16:16:56"}
{"order_id":5644,"customer_id":387,"amount":217.33,"order_time":"2025-09-09 16:26:56"}
{"order_id":5645,"customer_id":720,"amount":179.79,"order_time":"2025-09-09 16:36:56"}
{"order_id":5646,"customer_id":659,"amount":17.62,"order_time":"2025-09-09 16:46:56"}
{"order_id":5647,"customer_id":535,"amount":296.1,"order_time":"2025-09-09 16:56:56"}
{"order_id":5648,"customer_id":789,"amount":126.63,"order_time":"2025-09-09 17:06:56"}
{"order_id":5649,"customer_id":21,"amount":48.81,"order_time":"2025-09-09 17:16:56"}
{"order_id":5650,"customer_id":986,"amount":61.61,"order_time":"2025-09-09 17:26:56"}
{"order_id":5651,"customer_id":134,"amount":70.95,"order_time":"2025-09-09 17:36:56"}
{"order_id":5652,"customer_id":5,"amount":123.67,"order_time":"2025-09-09 17:46:56"}
{"order_id":5653,"customer_id":572,"amount":177.51,"order_time":"2025-09-09 17:56:56"}
{"order_id":5654,"customer_id":864,"amount":137.12,"order_time":"2025-09-09 18:06:56"}
{"order_id":5655,"customer_id":591,"amount":297.85,"order_time":"2025-09-09 18:16:56"}
{"order_id":5656,"customer_id":239,"amount":160.96,"order_time":"2025-09-09 18:26:56"}
{"order_id":5657,"customer_id":641,"amount":238.95,"order_time":"2025-09-09 18:36:56"}
{"order_id":5658,"customer_id":362,"amount":56.59,"order_time":"2025-09-09 18:46:56"}
{"order_id":5659,"customer_id":789,"amount":40.13,"order_time":"2025-09-09 18:56:56"}
{"order_id":5660,"customer_id":198,"amount":165.78,"order_time":"2025-09-09 19:06:56"}
{"order_id":5661,"customer_id":85,"amount":247.4,"order_time":"2025-09-09 19:16:56"}
{"order_id":5662,"customer_id":910,"amount":25.71,"order_time":"2025-09-09 19:26:56"}
{"order_id":5663,"customer_id":865,"amount":41.79,"order_time":"2025-09-09 19:36:56"}
{"order_id":5664,"customer_id":898,"amount":115.08,"order_time":"2025-09-09 19:46:56"}
{"order_id":5665,"customer_id":426,"amount":215.35,"order_time":"2025-09-09 19:56:56"}
{"order_id":5666,"customer_id":397,"amount":177.3,"order_time":"2025-09-09 20:06:56"}
{"order_id":5667,"customer_id":337,"amount":70.9,"order_time":"2025-09-09 20:16:56"}
{"order_id":5668,"customer_id":402,"amount":119.15,"order_time":"2025-09-09 20:26:56"}
{"order_id":5669,"customer_id":153,"amount":108.64,"order_time":"2025-09-09 20:36:56"}
{"order_id":5670,"customer_id":248,"amount":87.6,"order_time":"2025-09-09 20:46:56"}
{"order_id":5671,"customer_id":6,"amount":115.86,"order_time":"2025-09-09 20:56:56"}
{"order_id":5672,"customer_id":169,"amount":51.42,"order_time":"2025-09-09 21:06:56"}
{"order_id":5673,"customer_id":732,"amount":45.36,"order_time":"2025-09-09 21:16:56"}
{"order_id":5674,"customer_id":555,"amount":138.62,"order_time":"2025-09-09 21:26:56"}
{"order_id":5675,"customer_id":698,"amount":44.64,"order_time":"2025-09-09 21:36:56"}
{"order_id":5676,"customer_id":935,"amount":272.05,"order_time":"2025-09-09 21:46:56"}
{"order_id":5677,"customer_id":304,"amount":181.07,"order_time":"2025-09-09 21:56:56"}
{"order_id":5678,"customer_id":969,"amount":174.68,"order_time":"2025-09-09 22:06:56"}
{"order_id":5679,"customer_id":334,"amount":261.9,"order_time":"2025-09-09 22:16:56"}
{"order_id":5680,"customer_id":329,"amount":225.76,"order_time":"2025-09-09 22:26:56"}
{"order_id":5681,"customer_id":568,"amount":155.86,"order_time":"2025-09-09 22:36:56"}
{"order_id":5682,"customer_id":708,"amount":128.54,"order_time":"2025-09-09 22:46:56"}
{"order_id":5683,"customer_id":103,"amount":20.63,"order_time":"2025-09-09 22:56:56"}
{"order_id":5684,"customer_id":958,"amount":145.79,"order_time":"2025-09-09 23:06:56"}
{"order_id":5685,"customer_id":617,"amount":133.59,"order_time":"2025-09-09 23:16:56"}
{"order_id":5686,"customer_id":728,"amount":104.97,"order_time":"2025-09-09 23:26:56"}
{"order_id":5687,"customer_id":18,"amount":178.23,"order_time":"2025-09-09 23:36:56"}
{"order_id":5688,"customer_id":353,"amount":253.1,"order_time":"2025-09-09 23:46:56"}
{"order_id":5689,"customer_id":166,"amount":13.11,"order_time":"2025-09-09 23:56:56"}
{"order_id":5690,"customer_id":528,"amount":42.74,"order_time":"2025-09-10 00:06:56"}
{"order_id":5691,"customer_id":624,"amount":69.0,"order_time":"2025-09-10 00:16:56"}
{"order_id":5692,"customer_id":685,"amount":28.08,"order_time":"2025-09-10 00:26:56"}
{"order_id":5693,"customer_id":252,"amount":214.16,"order_time":"2025-09-10 00:36:56"}
{"order_id":5694,"customer_id":428,"amount":245.49,"order_time":"2025-09-10 00:46:56"}
{"order_id":5695,"customer_id":688,"amount":197.17,"order_time":"2025-09-10 00:56:56"}
{"order_id":5696,"customer_id":714,"amount":140.9,"order_time":"2025-09-10 01:06:56"}
{"order_id":5697,"customer_id":624,"amount":228.14,"order_time":"2025-09-10 01:16:56"}
{"order_id":5698,"customer_id":894,"amount":176.0,"order_time":"2025-09-10 01:26:56"}
{"order_id":5699,"customer_id":117,"amount":168.31,"order_time":"2025-09-10 01:36:56"}
{"order_id":5700,"customer_id":776,"amount":26.09,"order_time":"2025-09-10 01:46:56"}
{"order_id":5701,"customer_id":471,"amount":247.44,"order_time":"2025-09-10 01:56:56"}
{"order_id":5702,"customer_id":362,"amount":36.69,"order_time":"2025-09-10 02:06:56"}
{"order_id":5703,"customer_id":735,"amount":74.25,"order_time":"2025-09-10 02:16:56"}
{"order_id":5704,"customer_id":216,"amount":107.42,"order_time":"2025-09-10 02:26:56"}
{"order_id":5705,"customer_id":612,"amount":132.77,"order_time":"2025-09-10 02:36:56"}
{"order_id":5706,"customer_id":858,"amount":213.84,"order_time":"2025-09-10 02:46:56"}
{"order_id":5707,"customer_id":420,"amount":84.58,"order_time":"2025-09-10 02:56:56"}
{"order_id":5708,"customer_id":98,"amount":61.21,"order_time":"2025-09-10 03:06:56"}
{"order_id":5709,"customer_id":340,"amount":62.9,"order_time":"2025-09-10 03:16:56"}
{"order_id":5710,"customer_id":328,"amount":10.67,"order_time":"2025-09-10 03:26:56"}
{"order_id":5711,"customer_id":63,"amount":21.51,"order_time":"2025-09-10 03:36:56"}
{"order_id":5712,"customer_id":799,"amount":138.94,"order_time":"2025-09-10 03:46:56"}
{"order_id":5713,"customer_id":829,"amount":179.82,"order_time":"2025-09-10 03:56:56"}
{"order_id":5714,"customer_id":517,"amount":107.41,"order_time":"2025-09-10 04:06:56"}
{"order_id":5715,"customer_id":581,"amount":146.16,"order_time":"2025-09-10 04:16:56"}
{"order_id":5716,"customer_id":910,"amount":6.94,"order_time":"2025-09-10 04:26:56"}
{"order_id":5717,"customer_id":479,"amount":59.0,"order_time":"2025-09-10 04:36:56"}
{"order_id":5718,"customer_id":964,"amount":94.82,"order_time":"2025-09-10 04:46:56"}
{"order_id":5719,"customer_id":306,"amount":169.62,"order_time":"2025-09-10 04:56:56"}
{"order_id":5720,"customer_id":97,"amount":52.97,"order_time":"2025-09-10 05:06:56"}
{"order_id":5721,"customer_id":752,"amount":130.01,"order_time":"2025-09-10 05:16:56"}
{"order_id":5722,"customer_id":904,"amount":54.18,"order_time":"2025-09-10 05:26:56"}
{"order_id":5723,"customer_id":775,"amount":36.53,"order_time":"2025-09-10 05:36:56"}
{"order_id":5724,"customer_id":53,"amount":7.52,"order_time":"2025-09-10 05:46:56"}
{"order_id":5725,"customer_id":563,"amount":180.76,"order_time":"2025-09-10 05:56:56"}
{"order_id":5726,"customer_id":663,"amount":107.97,"order_time":"2025-09-10 06:06:56"}
{"order_id":5727,"customer_id":169,"amount":22.97,"order_time":"2025-09-10 06:16:56"}
{"order_id":5728,"customer_id":2,"amount":109.69,"order_time":"2025-09-10 06:26:56"}
{"order_id":5729,"customer_id":488,"amount":262.71,"order_time":"2025-09-10 06:36:56"}
{"order_id":5730,"customer_id":78,"amount":270.81,"order_time":"2025-09-10 06:46:56"}
{"order_id":5731,"customer_id":565,"amount":230.69,"order_time":"2025-09-10 06:56:56"}
{"order_id":5732,"customer_id":625,"amount":207.33,"order_time":"2025-09-10 07:06:56"}
{"order_id":5733,"customer_id":503,"amount":238.3,"order_time":"2025-09-10 07:16:56"}
{"order_id":5734,"customer_id":40,"amount":95.86,"order_time":"2025-09-10 07:26:56"}
{"order_id":5735,"customer_id":373,"amount":9.44,"order_time":"2025-09-10 07:36:56"}
{"order_id":5736,"customer_id":494,"amount":215.49,"order_time":"2025-09-10 07:46:56"}
{"order_id":5737,"customer_id":49,"amount":204.41,"order_time":"2025-09-10 07:56:56"}
{"order_id":5738,"customer_id":939,"amount":297.07,"order_time":"2025-09-10 08:06:56"}
{"order_id":5739,"customer_id":897,"amount":40.58,"order_time":"2025-09-10 08:16:56"}
{"order_id":5740,"customer_id":539,"amount":238.17,"order_time":"2025-09-10 08:26:56"}
{"order_id":5741,"customer_id":796,"amount":258.51,"order_time":"2025-09-10 08:36:56"}
{"order_id":5742,"customer_id":421,"amount":281.67,"order_time":"2025-09-10 08:46:56"}
{"order_id":5743,"customer_id":152,"amount":291.23,"order_time":"2025-09-10 08:56:56"}
{"order_id":5744,"customer_id":871,"amount":237.05,"order_time":"2025-09-10 09:06:56"}
{"order_id":5745,"customer_id":484,"amount":225.2,"order_time":"2025-09-10 09:16:56"}
{"order_id":5746,"customer_id":42,"amount":273.71,"order_time":"2025-09-10 09:26:56"}
{"order_id":5747,"customer_id":827,"amount":138.51,"order_time":"2025-09-10 09:36:56"}
{"order_id":5748,"customer_id":726,"amount":14.1,"order_time":"2025-09-10 09:46:56"}
{"order_id":5749,"customer_id":576,"amount":113.71,"order_time":"2025-09-10 09:56:56"}
{"order_id":5750,"customer_id":18,"amount":171.17,"order_time":"2025-09-10 10:06:56"}
{"order_id":5751,"customer_id":780,"amount":50.63,"order_time":"2025-09-10 10:16:56"}
{"order_id":5752,"customer_id":48,"amount":135.54,"order_time":"2025-09-10 10:26:56"}
{"order_id":5753,"customer_id":662,"amount":280.14,"order_time":"2025-09-10 10:36:56"}
{"order_id":5754,"customer_id":924,"amount":190.6,"order_time":"2025-09-10 10:46:56"}
{"order_id":5755,"customer_id":129,"amount":249.33,"order_time":"2025-09-10 10:56:56"}
{"order_id":5756,"customer_id":769,"amount":227.63,"order_time":"2025-09-10 11:06:56"}
{"order_id":5757,"customer_id":359,"amount":107.77,"order_time":"2025-09-10 11:16:56"}
{"order_id":5758,"customer_id":385,"amount":246.21,"order_time":"2025-09-10 11:26:56"}
{"order_id":5759,"customer_id":298,"amount":133.71,"order_time":"2025-09-10 11:36:56"}
{"order_id":5760,"customer_id":626,"amount":142.84,"order_time":"2025-09-10 11:46:56"}
{"order_id":5761,"customer_id":51,"amount":47.28,"order_time":"2025-09-10 11:56:56"}
{"order_id":5762,"customer_id":723,"amount":163.74,"order_time":"2025-09-10 12:06:56"}
{"order_id":5763,"customer_id":6,"amount":256.08,"order_time":"2025-09-10 12:16:56"}
{"order_id":5764,"customer_id":115,"amount":50.31,"order_time":"2025-09-10 12:26:56"}
{"order_id":5765,"customer_id":519,"amount":210.17,"order_time":"2025-09-10 12:36:56"}
{"order_id":5766,"customer_id":856,"amount":203.87,"order_time":"2025-09-10 12:46:56"}
{"order_id":5767,"customer_id":832,"amount":31.4,"order_time":"2025-09-10 12:56:56"}
{"order_id":5768,"customer_id":110,"amount":187.77,"order_time":"2025-09-10 13:06:56"}
{"order_id":5769,"customer_id":557,"amount":22.73,"order_time":"2025-09-10 13:16:56"}
{"order_id":5770,"customer_id":265,"amount":261.09,"order_time":"2025-09-10 13:26:56"}
{"order_id":5771,"customer_id":342,"amount":214.49,"order_time":"2025-09-10 13:36:56"}
{"order_id":5772,"customer_id":617,"amount":206.99,"order_time":"2025-09-10 13:46:56"}
{"order_id":5773,"customer_id":457,"amount":188.02,"order_time":"2025-09-10 13:56:56"}
{"order_id":5774,"customer_id":363,"amount":272.41,"order_time":"2025-09-10 14:06:56"}
{"order_id":5775,"customer_id":997,"amount":289.18,"order_time":"2025-09-10 14:16:56"}
{"order_id":5776,"customer_id":789,"amount":91.45,"order_time":"2025-09-10 14:26:56"}
{"order_id":5777,"customer_id":47,"amount":109.17,"order_time":"2025-09-10 14:36:56"}
{"order_id":5778,"customer_id":287,"amount":259.76,"order_time":"2025-09-10 14:46:56"}
{"order_id":5779,"customer_id":315,"amount":196.89,"order_time":"2025-09-10 14:56:56"}
{"order_id":5780,"customer_id":554,"amount":180.36,"order_time":"2025-09-10 15:06:56"}
{"order_id":5781,"customer_id":993,"amount":169.91,"order_time":"2025-09-10 15:16:56"}
{"order_id":5782,"customer_id":296,"amount":131.17,"order_time":"2025-09-10 15:26:56"}
{"order_id":5783,"customer_id":21,"amount":56.01,"order_time":"2025-09-10 15:36:56"}
{"order_id":5784,"customer_id":295,"amount":223.2,"order_time":"2025-09-10 15:46:56"}
{"order_id":5785,"customer_id":728,"amount":233.92,"order_time":"2025-09-10 15:56:56"}
{"order_id":5786,"customer_id":326,"amount":75.3,"order_time":"2025-09-10 16:06:56"}
{"order_id":5787,"customer_id":846,"amount":227.64,"order_time":"2025-09-10 16:16:56"}
{"order_id":5788,"customer_id":409,"amount":296.53,"order_time":"2025-09-10 16:26:56"}
{"order_id":5789,"customer_id":584,"amount":201.17,"order_time":"2025-09-10 16:36:56"}
{"order_id":5790,"customer_id":951,"amount":10.76,"order_time":"2025-09-10 16:46:56"}
{"order_id":5791,"customer_id":25,"amount":179.12,"order_time":"2025-09-10 16:56:56"}
{"order_id":5792,"customer_id":635,"amount":111.8,"order_time":"2025-09-10 17:06:56"}
{"order_id":5793,"customer_id":656,"amount":238.41,"order_time":"2025-09-10 17:16:56"}
{"order_id":5794,"customer_id":50,"amount":120.93,"order_time":"2025-09-10 17:26:56"}
{"order_id":5795,"customer_id":462,"amount":67.33,"order_time":"2025-09-10 17:36:56"}
{"order_id":5796,"customer_id":600,"amount":201.45,"order_time":"2025-09-10 17:46:56"}
{"order_id":5797,"customer_id":912,"amount":281.94,"order_time":"2025-09-10 17:56:56"}
{"order_id":5798,"customer_id":48,"amount":134.28,"order_time":"2025-09-10 18:06:56"}
{"order_id":5799,"customer_id":823,"amount":103.25,"order_time":"2025-09-10 18:16:56"}
{"order_id":5800,"customer_id":912,"amount":91.3,"order_time":"2025-09-10 18:26:56"}
{"order_id":5801,"customer_id":300,"amount":284.22,"order_time":"2025-09-10 18:36:56"}
{"order_id":5802,"customer_id":15,"amount":192.4,"order_time":"2025-09-10 18:46:56"}
{"order_id":5803,"customer_id":201,"amount":117.92,"order_time":"2025-09-10 18:56:56"}
{"order_id":5804,"customer_id":497,"amount":124.12,"order_time":"2025-09-10 19:06:56"}
{"order_id":5805,"customer_id":69,"amount":87.63,"order_time":"2025-09-10 19:16:56"}
{"order_id":5806,"customer_id":742,"amount":68.76,"order_time":"2025-09-10 19:26:56"}
{"order_id":5807,"customer_id":185,"amount":136.05,"order_time":"2025-09-10 19:36:56"}
{"order_id":5808,"customer_id":2,"amount":30.71,"order_time":"2025-09-10 19:46:56"}
{"order_id":5809,"customer_id":938,"amount":74.46,"order_time":"2025-09-10 19:56:56"}
{"order_id":5810,"customer_id":364,"amount":193.63,"order_time":"2025-09-10 20:06:56"}
{"order_id":5811,"customer_id":148,"amount":262.93,"order_time":"2025-09-10 20:16:56"}
{"order_id":5812,"customer_id":670,"amount":78.79,"order_time":"2025-09-10 20:26:56"}
{"order_id":5813,"customer_id":681,"amount":229.23,"order_time":"2025-09-10 20:36:56"}
{"order_id":5814,"customer_id":193,"amount":108.53,"order_time":"2025-09-10 20:46:56"}
{"order_id":5815,"customer_id":36,"amount":98.65,"order_time":"2025-09-10 20:56:56"}
{"order_id":5816,"customer_id":236,"amount":79.93,"order_time":"2025-09-10 21:06:56"}
{"order_id":5817,"customer_id":625,"amount":279.62,"order_time":"2025-09-10 21:16:56"}
{"order_id":5818,"customer_id":178,"amount":87.84,"order_time":"2025-09-10 21:26:56"}
{"order_id":5819,"customer_id":283,"amount":9.03,"order_time":"2025-09-10 21:36:56"}
{"order_id":5820,"customer_id":260,"amount":163.71,"order_time":"2025-09-10 21:46:56"}
{"order_id":5821,"customer_id":673,"amount":146.5,"order_time":"2025-09-10 21:56:56"}
{"order_id":5822,"customer_id":816,"amount":177.31,"order_time":"2025-09-10 22:06:56"}
{"order_id":5823,"customer_id":613,"amount":33.84,"order_time":"2025-09-10 22:16:56"}
{"order_id":5824,"customer_id":973,"amount":291.04,"order_time":"2025-09-10 22:26:56"}
{"order_id":5825,"customer_id":911,"amount":144.83,"order_time":"2025-09-10 22:36:56"}
{"order_id":5826,"customer_id":420,"amount":245.56,"order_time":"2025-09-10 22:46:56"}
{"order_id":5827,"customer_id":552,"amount":221.46,"order_time":"2025-09-10 22:56:56"}
{"order_id":5828,"customer_id":464,"amount":25.42,"order_time":"2025-09-10 23:06:56"}
{"order_id":5829,"customer_id":541,"amount":158.67,"order_time":"2025-09-10 23:16:56"}
{"order_id":5830,"customer_id":893,"amount":64.46,"order_time":"2025-09-10 23:26:56"}
{"order_id":5831,"customer_id":395,"amount":170.51,"order_time":"2025-09-10 23:36:56"}
{"order_id":5832,"customer_id":151,"amount":238.78,"order_time":"2025-09-10 23:46:56"}
{"order_id":5833,"customer_id":128,"amount":258.21,"order_time":"2025-09-10 23:56:56"}
{"order_id":5834,"customer_id":930,"amount":69.63,"order_time":"2025-09-11 00:06:56"}
{"order_id":5835,"customer_id":686,"amount":103.76,"order_time":"2025-09-11 00:16:56"}
{"order_id":5836,"customer_id":934,"amount":276.51,"order_time":"2025-09-11 00:26:56"}
{"order_id":5837,"customer_id":532,"amount":67.21,"order_time":"2025-09-11 00:36:56"}
{"order_id":5838,"customer_id":37,"amount":122.5,"order_time":"2025-09-11 00:46:56"}
{"order_id":5839,"customer_id":471,"amount":223.92,"order_time":"2025-09-11 00:56:56"}
{"order_id":5840,"customer_id":261,"amount":153.2,"order_time":"2025-09-11 01:06:56"}
{"order_id":5841,"customer_id":285,"amount":121.12,"order_time":"2025-09-11 01:16:56"}
{"order_id":5842,"customer_id":460,"amount":264.33,"order_time":"2025-09-11 01:26:56"}
{"order_id":5843,"customer_id":678,"amount":276.88,"order_time":"2025-09-11 01:36:56"}
{"order_id":5844,"customer_id":144,"amount":48.24,"order_time":"2025-09-11 01:46:56"}
{"order_id":5845,"customer_id":269,"amount":39.73,"order_time":"2025-09-11 01:56:56"}
{"order_id":5846,"customer_id":204,"amount":101.06,"order_time":"2025-09-11 02:06:56"}
{"order_id":5847,"customer_id":780,"amount":184.25,"order_time":"2025-09-11 02:16:56"}
{"order_id":5848,"customer_id":503,"amount":126.91,"order_time":"2025-09-11 02:26:56"}
{"order_id":5849,"customer_id":148,"amount":130.93,"order_time":"2025-09-11 02:36:56"}
{"order_id":5850,"customer_id":440,"amount":13.26,"order_time":"2025-09-11 02:46:56"}
{"order_id":5851,"customer_id":326,"amount":40.35,"order_time":"2025-09-11 02:56:56"}
{"order_id":5852,"customer_id":976,"amount":239.47,"order_time":"2025-09-11 03:06:56"}
{"order_id":5853,"customer_id":578,"amount":113.96,"order_time":"2025-09-11 03:16:56"}
{"order_id":5854,"customer_id":548,"amount":112.3,"order_time":"2025-09-11 03:26:56"}
{"order_id":5855,"customer_id":860,"amount":155.24,"order_time":"2025-09-11 03:36:56"}
{"order_id":5856,"customer_id":911,"amount":53.71,"order_time":"2025-09-11 03:46:56"}
{"order_id":5857,"customer_id":2,"amount":170.29,"order_time":"2025-09-11 03:56:56"}
{"order_id":5858,"customer_id":175,"amount":70.52,"order_time":"2025-09-11 04:06:56"}
{"order_id":5859,"customer_id":30,"amount":263.48,"order_time":"2025-09-11 04:16:56"}
{"order_id":5860,"customer_id":658,"amount":102.5,"order_time":"2025-09-11 04:26:56"}
{"order_id":5861,"customer_id":334,"amount":277.2,"order_time":"2025-09-11 04:36:56"}
{"order_id":5862,"customer_id":305,"amount":116.37,"order_time":"2025-09-11 04:46:56"}
{"order_id":5863,"customer_id":271,"amount":71.5,"order_time":"2025-09-11 04:56:56"}
{"order_id":5864,"customer_id":755,"amount":106.34,"order_time":"2025-09-11 05:06:56"}
{"order_id":5865,"customer_id":296,"amount":217.28,"order_time":"2025-09-11 05:16:56"}
{"order_id":5866,"customer_id":644,"amount":176.41,"order_time":"2025-09-11 05:26:56"}
{"order_id":5867,"customer_id":310,"amount":278.13,"order_time":"2025-09-11 05:36:56"}
{"order_id":5868,"customer_id":927,"amount":266.89,"order_time":"2025-09-11 05:46:56"}
{"order_id":5869,"customer_id":384,"amount":276.57,"order_time":"2025-09-11 05:56:56"}
{"order_id":5870,"customer_id":775,"amount":35.92,"order_time":"2025-09-11 06:06:56"}
{"order_id":5871,"customer_id":449,"amount":187.56,"order_time":"2025-09-11 06:16:56"}
{"order_id":5872,"customer_id":812,"amount":203.71,"order_time":"2025-09-11 06:26:56"}
{"order_id":5873,"customer_id":123,"amount":291.76,"order_time":"2025-09-11 06:36:56"}
{"order_id":5874,"customer_id":468,"amount":221.12,"order_time":"2025-09-11 06:46:56"}
{"order_id":5875,"customer_id":482,"amount":131.41,"order_time":"2025-09-11 06:56:56"}
{"order_id":5876,"customer_id":886,"amount":121.03,"order_time":"2025-09-11 07:06:56"}
{"order_id":5877,"customer_id":740,"amount":176.44,"order_time":"2025-09-11 07:16:56"}
{"order_id":5878,"customer_id":357,"amount":229.79,"order_time":"2025-09-11 07:26:56"}
{"order_id":5879,"customer_id":342,"amount":75.58,"order_time":"2025-09-11 07:36:56"}
{"order_id":5880,"customer_id":851,"amount":199.85,"order_time":"2025-09-11 07:46:56"}
{"order_id":5881,"customer_id":478,"amount":132.53,"order_time":"2025-09-11 07:56:56"}
{"order_id":5882,"customer_id":73,"amount":98.3,"order_time":"2025-09-11 08:06:56"}
{"order_id":5883,"customer_id":112,"amount":262.32,"order_time":"2025-09-11 08:16:56"}
{"order_id":5884,"customer_id":848,"amount":143.19,"order_time":"2025-09-11 08:26:56"}
{"order_id":5885,"customer_id":453,"amount":78.84,"order_time":"2025-09-11 08:36:56"}
{"order_id":5886,"customer_id":745,"amount":233.75,"order_time":"2025-09-11 08:46:56"}
{"order_id":5887,"customer_id":908,"amount":244.17,"order_time":"2025-09-11 08:56:56"}
{"order_id":5888,"customer_id":923,"amount":204.54,"order_time":"2025-09-11 09:06:56"}
{"order_id":5889,"customer_id":122,"amount":59.0,"order_time":"2025-09-11 09:16:56"}
{"order_id":5890,"customer_id":39,"amount":68.45,"order_time":"2025-09-11 09:26:56"}
{"order_id":5891,"customer_id":299,"amount":164.2,"order_time":"2025-09-11 09:36:56"}
{"order_id":5892,"customer_id":578,"amount":22.12,"order_time":"2025-09-11 09:46:56"}
{"order_id":5893,"customer_id":251,"amount":295.58,"order_time":"2025-09-11 09:56:56"}
{"order_id":5894,"customer_id":494,"amount":176.98,"order_time":"2025-09-11 10:06:56"}
{"order_id":5895,"customer_id":171,"amount":266.78,"order_time":"2025-09-11 10:16:56"}
{"order_id":5896,"customer_id":878,"amount":252.78,"order_time":"2025-09-11 10:26:56"}
{"order_id":5897,"customer_id":855,"amount":114.78,"order_time":"2025-09-11 10:36:56"}
{"order_id":5898,"customer_id":946,"amount":221.91,"order_time":"2025-09-11 10:46:56"}
{"order_id":5899,"customer_id":830,"amount":239.13,"order_time":"2025-09-11 10:56:56"}
{"order_id":5900,"customer_id":124,"amount":258.09,"order_time":"2025-09-11 11:06:56"}
{"order_id":5901,"customer_id":538,"amount":287.11,"order_time":"2025-09-11 11:16:56"}
{"order_id":5902,"customer_id":691,"amount":6.44,"order_time":"2025-09-11 11:26:56"}
{"order_id":5903,"customer_id":765,"amount":280.15,"order_time":"2025-09-11 11:36:56"}
{"order_id":5904,"customer_id":722,"amount":240.87,"order_time":"2025-09-11 11:46:56"}
{"order_id":5905,"customer_id":725,"amount":137.24,"order_time":"2025-09-11 11:56:56"}
{"order_id":5906,"customer_id":285,"amount":139.13,"order_time":"2025-09-11 12:06:56"}
{"order_id":5907,"customer_id":368,"amount":210.53,"order_time":"2025-09-11 12:16:56"}
{"order_id":5908,"customer_id":920,"amount":284.06,"order_time":"2025-09-11 12:26:56"}
{"order_id":5909,"customer_id":499,"amount":299.07,"order_time":"2025-09-11 12:36:56"}
{"order_id":5910,"customer_id":84,"amount":75.8,"order_time":"2025-09-11 12:46:56"}
{"order_id":5911,"customer_id":837,"amount":113.87,"order_time":"2025-09-11 12:56:56"}
{"order_id":5912,"customer_id":687,"amount":237.54,"order_time":"2025-09-11 13:06:56"}
{"order_id":5913,"customer_id":425,"amount":134.29,"order_time":"2025-09-11 13:16:56"}
{"order_id":5914,"customer_id":908,"amount":47.91,"order_time":"2025-09-11 13:26:56"}
{"order_id":5915,"customer_id":869,"amount":96.98,"order_time":"2025-09-11 13:36:56"}
{"order_id":5916,"customer_id":640,"amount":46.74,"order_time":"2025-09-11 13:46:56"}
{"order_id":5917,"customer_id":292,"amount":272.27,"order_time":"2025-09-11 13:56:56"}
{"order_id":5918,"customer_id":636,"amount":67.93,"order_time":"2025-09-11 14:06:56"}
{"order_id":5919,"customer_id":711,"amount":240.06,"order_time":"2025-09-11 14:16:56"}
{"order_id":5920,"customer_id":12,"amount":290.72,"order_time":"2025-09-11 14:26:56"}
{"order_id":5921,"customer_id":819,"amount":72.31,"order_time":"2025-09-11 14:36:56"}
{"order_id":5922,"customer_id":567,"amount":117.76,"order_time":"2025-09-11 14:46:56"}
{"order_id":5923,"customer_id":590,"amount":10.27,"order_time":"2025-09-11 14:56:56"}
{"order_id":5924,"customer_id":525,"amount":174.47,"order_time":"2025-09-11 15:06:56"}
{"order_id":5925,"customer_id":663,"amount":156.55,"order_time":"2025-09-11 15:16:56"}
{"order_id":5926,"customer_id":651,"amount":51.83,"order_time":"2025-09-11 15:26:56"}
{"order_id":5927,"customer_id":728,"amount":198.53,"order_time":"2025-09-11 15:36:56"}
{"order_id":5928,"customer_id":291,"amount":92.55,"order_time":"2025-09-11 15:46:56"}
{"order_id":5929,"customer_id":799,"amount":115.31,"order_time":"2025-09-11 15:56:56"}
{"order_id":5930,"customer_id":166,"amount":255.17,"order_time":"2025-09-11 16:06:56"}
{"order_id":5931,"customer_id":976,"amount":146.13,"order_time":"2025-09-11 16:16:56"}
{"order_id":5932,"customer_id":106,"amount":177.37,"order_time":"2025-09-11 16:26:56"}
{"order_id":5933,"customer_id":684,"amount":93.78,"order_time":"2025-09-11 16:36:56"}
{"order_id":5934,"customer_id":309,"amount":42.98,"order_time":"2025-09-11 16:46:56"}
{"order_id":5935,"customer_id":739,"amount":28.37,"order_time":"2025-09-11 16:56:56"}
{"order_id":5936,"customer_id":58,"amount":152.81,"order_time":"2025-09-11 17:06:56"}
{"order_id":5937,"customer_id":33,"amount":257.72,"order_time":"2025-09-11 17:16:56"}
{"order_id":5938,"customer_id":40,"amount":13.69,"order_time":"2025-09-11 17:26:56"}
{"order_id":5939,"customer_id":243,"amount":178.22,"order_time":"2025-09-11 17:36:56"}
{"order_id":5940,"customer_id":876,"amount":11.25,"order_time":"2025-09-11 17:46:56"}
{"order_id":5941,"customer_id":132,"amount":237.77,"order_time":"2025-09-11 17:56:56"}
{"order_id":5942,"customer_id":251,"amount":169.63,"order_time":"2025-09-11 18:06:56"}
{"order_id":5943,"customer_id":778,"amount":287.87,"order_time":"2025-09-11 18:16:56"}
{"order_id":5944,"customer_id":753,"amount":191.42,"order_time":"2025-09-11 18:26:56"}
{"order_id":5945,"customer_id":351,"amount":225.73,"order_time":"2025-09-11 18:36:56"}
{"order_id":5946,"customer_id":905,"amount":283.57,"order_time":"2025-09-11 18:46:56"}
{"order_id":5947,"customer_id":914,"amount":47.15,"order_time":"2025-09-11 18:56:56"}
{"order_id":5948,"customer_id":76,"amount":146.7,"order_time":"2025-09-11 19:06:56"}
{"order_id":5949,"customer_id":915,"amount":103.75,"order_time":"2025-09-11 19:16:56"}
{"order_id":5950,"customer_id":517,"amount":64.9,"order_time":"2025-09-11 19:26:56"}
{"order_id":5951,"customer_id":507,"amount":268.73,"order_time":"2025-09-11 19:36:56"}
{"order_id":5952,"customer_id":236,"amount":13.05,"order_time":"2025-09-11 19:46:56"}
{"order_id":5953,"customer_id":510,"amount":11.37,"order_time":"2025-09-11 19:56:56"}
{"order_id":5954,"customer_id":443,"amount":254.36,"order_time":"2025-09-11 20:06:56"}
{"order_id":5955,"customer_id":173,"amount":253.65,"order_time":"2025-09-11 20:16:56"}
{"order_id":5956,"customer_id":129,"amount":234.34,"order_time":"2025-09-11 20:26:56"}
{"order_id":5957,"customer_id":98,"amount":213.63,"order_time":"2025-09-11 20:36:56"}
{"order_id":5958,"customer_id":874,"amount":38.55,"order_time":"2025-09-11 20:46:56"}
{"order_id":5959,"customer_id":491,"amount":52.52,"order_time":"2025-09-11 20:56:56"}
{"order_id":5960,"customer_id":864,"amount":209.11,"order_time":"2025-09-11 21:06:56"}
{"order_id":5961,"customer_id":269,"amount":18.18,"order_time":"2025-09-11 21:16:56"}
{"order_id":5962,"customer_id":604,"amount":216.36,"order_time":"2025-09-11 21:26:56"}
{"order_id":5963,"customer_id":841,"amount":212.37,"order_time":"2025-09-11 21:36:56"}
{"order_id":5964,"customer_id":215,"amount":189.97,"order_time":"2025-09-11 21:46:56"}
{"order_id":5965,"customer_id":854,"amount":48.31,"order_time":"2025-09-11 21:56:56"}
{"order_id":5966,"customer_id":95,"amount":240.12,"order_time":"2025-09-11 22:06:56"}
{"order_id":5967,"customer_id":854,"amount":167.67,"order_time":"2025-09-11 22:16:56"}
{"order_id":5968,"customer_id":718,"amount":239.17,"order_time":"2025-09-11 22:26:56"}
{"order_id":5969,"customer_id":390,"amount":262.2,"order_time":"2025-09-11 22:36:56"}
{"order_id":5970,"customer_id":969,"amount":287.54,"order_time":"2025-09-11 22:46:56"}
{"order_id":5971,"customer_id":171,"amount":74.19,"order_time":"2025-09-11 22:56:56"}
{"order_id":5972,"customer_id":64,"amount":73.5,"order_time":"2025-09-11 23:06:56"}
{"order_id":5973,"customer_id":929,"amount":160.69,"order_time":"2025-09-11 23:16:56"}
{"order_id":5974,"customer_id":297,"amount":140.08,"order_time":"2025-09-11 23:26:56"}
{"order_id":5975,"customer_id":222,"amount":173.35,"order_time":"2025-09-11 23:36:56"}
{"order_id":5976,"customer_id":799,"amount":54.92,"order_time":"2025-09-11 23:46:56"}
{"order_id":5977,"customer_id":197,"amount":193.27,"order_time":"2025-09-11 23:56:56"}
{"order_id":5978,"customer_id":581,"amount":273.69,"order_time":"2025-09-12 00:06:56"}
{"order_id":5979,"customer_id":491,"amount":215.88,"order_time":"2025-09-12 00:16:56"}
{"order_id":5980,"customer_id":976,"amount":147.88,"order_time":"2025-09-12 00:26:56"}
{"order_id":5981,"customer_id":609,"amount":122.39,"order_time":"2025-09-12 00:36:56"}
{"order_id":5982,"customer_id":526,"amount":208.79,"order_time":"2025-09-12 00:46:56"}
{"order_id":5983,"customer_id":531,"amount":287.56,"order_time":"2025-09-12 00:56:56"}
{"order_id":5984,"customer_id":394,"amount":111.22,"order_time":"2025-09-12 01:06:56"}
{"order_id":5985,"customer_id":324,"amount":195.53,"order_time":"2025-09-12 01:16:56"}
{"order_id":5986,"customer_id":94,"amount":298.99,"order_time":"2025-09-12 01:26:56"}
{"order_id":5987,"customer_id":729,"amount":87.75,"order_time":"2025-09-12 01:36:56"}
{"order_id":5988,"customer_id":659,"amount":236.02,"order_time":"2025-09-12 01:46:56"}
{"order_id":5989,"customer_id":580,"amount":235.14,"order_time":"2025-09-12 01:56:56"}
{"order_id":5990,"customer_id":882,"amount":213.08,"order_time":"2025-09-12 02:06:56"}
{"order_id":5991,"customer_id":725,"amount":252.0,"order_time":"2025-09-12 02:16:56"}
{"order_id":5992,"customer_id":865,"amount":115.59,"order_time":"2025-09-12 02:26:56"}
{"order_id":5993,"customer_id":813,"amount":114.52,"order_time":"2025-09-12 02:36:56"}
{"order_id":5994,"customer_id":352,"amount":108.32,"order_time":"2025-09-12 02:46:56"}
{"order_id":5995,"customer_id":601,"amount":261.89,"order_time":"2025-09-12 02:56:56"}
{"order_id":5996,"customer_id":463,"amount":112.48,"order_time":"2025-09-12 03:06:56"}
{"order_id":5997,"customer_id":1,"amount":158.64,"order_time":"2025-09-12 03:16:56"}
{"order_id":5998,"customer_id":575,"amount":235.56,"order_time":"2025-09-12 03:26:56"}
{"order_id":5999,"customer_id":774,"amount":63.88,"order_time":"2025-09-12 03:36:56"}
{"order_id":6000,"customer_id":609,"amount":60.81,"order_time":"2025-09-12 03:46:56"}
